{"_env":"NODEJS","_serializationMethod":"normal","_autosave":false,"_autosaveInterval":5000,"_collections":[{"name":"items","unindexedSortComparator":"js","defaultLokiOperatorPackage":"js","_dynamicViews":[],"uniqueNames":[],"transforms":{},"rangedIndexes":{},"_data":[{"slug":"credits","description":"Packages and media used by RockBand.","title":"Credits","order":2,"date":"2021-08-01T17:00:34.000Z","container":"text-center","showToC":false,"toc":[{"id":"writerdeveloper","depth":2,"text":"Writer/Developer"},{"id":"built-with","depth":2,"text":"Built With"},{"id":"fonts","depth":2,"text":"Fonts"},{"id":"hosting","depth":2,"text":"Hosting"}],"body":{"type":"root","children":[{"type":"element","tag":"h2","props":{"id":"writerdeveloper"},"children":[{"type":"element","tag":"a","props":{"ariaHidden":"true","href":"#writerdeveloper","tabIndex":-1},"children":[{"type":"element","tag":"span","props":{"className":["icon","icon-link"]},"children":[]}]},{"type":"text","value":"Writer/Developer"}]},{"type":"text","value":"\n"},{"type":"element","tag":"p","props":{},"children":[{"type":"element","tag":"a","props":{"href":"https://thombruce.com/","className":["text-3xl","font-light"]},"children":[{"type":"text","value":"Thom Bruce"}]}]},{"type":"text","value":"\n"},{"type":"element","tag":"br","props":{},"children":[]},{"type":"text","value":"\n"},{"type":"element","tag":"br","props":{},"children":[]},{"type":"text","value":"\n"},{"type":"element","tag":"h2","props":{"id":"built-with"},"children":[{"type":"element","tag":"a","props":{"ariaHidden":"true","href":"#built-with","tabIndex":-1},"children":[{"type":"element","tag":"span","props":{"className":["icon","icon-link"]},"children":[]}]},{"type":"text","value":"Built With"}]},{"type":"text","value":"\n"},{"type":"element","tag":"p","props":{},"children":[{"type":"element","tag":"a","props":{"href":"https://nuxtjs.org/","className":["text-2xl"]},"children":[{"type":"element","tag":"rock-band-simple-icon","props":{"icon":"nuxtdotjs"},"children":[]},{"type":"text","value":" Nuxt.js"}]},{"type":"text","value":"\n"},{"type":"element","tag":"br","props":{"className":["inline","md:hidden"]},"children":[]},{"type":"element","tag":"span","props":{"className":["hidden","md:inline"]},"children":[{"type":"text","value":" "}]},{"type":"text","value":"\n"},{"type":"element","tag":"a","props":{"href":"https://tailwindcss.com/","className":["text-2xl"]},"children":[{"type":"element","tag":"rock-band-simple-icon","props":{"icon":"tailwindcss"},"children":[]},{"type":"text","value":" Tailwind CSS"}]}]},{"type":"text","value":"\n"},{"type":"element","tag":"br","props":{},"children":[]},{"type":"text","value":"\n"},{"type":"element","tag":"br","props":{},"children":[]},{"type":"text","value":"\n"},{"type":"element","tag":"h2","props":{"id":"fonts"},"children":[{"type":"element","tag":"a","props":{"ariaHidden":"true","href":"#fonts","tabIndex":-1},"children":[{"type":"element","tag":"span","props":{"className":["icon","icon-link"]},"children":[]}]},{"type":"text","value":"Fonts"}]},{"type":"text","value":"\n"},{"type":"element","tag":"p","props":{},"children":[{"type":"element","tag":"a","props":{"href":"https://fontawesome.com/"},"children":[{"type":"element","tag":"rock-band-simple-icon","props":{"icon":"fontawesome"},"children":[]},{"type":"text","value":" Font Awesome"}]},{"type":"text","value":"\n"},{"type":"element","tag":"br","props":{"className":["inline","md:hidden"]},"children":[]},{"type":"element","tag":"span","props":{"className":["hidden","md:inline"]},"children":[{"type":"text","value":" "}]},{"type":"text","value":"\n"},{"type":"element","tag":"a","props":{"href":"https://simpleicons.org/"},"children":[{"type":"element","tag":"rock-band-simple-icon","props":{"icon":"simpleicons"},"children":[]},{"type":"text","value":" Simple Icons"}]}]},{"type":"text","value":"\n"},{"type":"element","tag":"h2","props":{"id":"hosting"},"children":[{"type":"element","tag":"a","props":{"ariaHidden":"true","href":"#hosting","tabIndex":-1},"children":[{"type":"element","tag":"span","props":{"className":["icon","icon-link"]},"children":[]}]},{"type":"text","value":"Hosting"}]},{"type":"text","value":"\n"},{"type":"element","tag":"p","props":{},"children":[{"type":"element","tag":"a","props":{"href":"https://github.com/","className":["text-2xl","font-light"]},"children":[{"type":"element","tag":"rock-band-simple-icon","props":{"icon":"github"},"children":[]},{"type":"text","value":" GitHub"}]}]}]},"text":"\n## Writer/Developer\n\n<a href='https://thombruce.com/' class='text-3xl font-light'>Thom Bruce</a>\n\n<br/>\n<br/>\n\n## Built With\n\n<a href='https://nuxtjs.org/' class='text-2xl'><rock-band-simple-icon icon='nuxtdotjs'></rock-band-simple-icon> Nuxt.js</a>\n<br class='inline md:hidden'/><span class='hidden md:inline'>&emsp;</span>\n<a href='https://tailwindcss.com/' class='text-2xl'><rock-band-simple-icon icon='tailwindcss'></rock-band-simple-icon> Tailwind CSS</a>\n\n<br/>\n<br/>\n\n## Fonts\n\n<a href='https://fontawesome.com/'><rock-band-simple-icon icon='fontawesome'></rock-band-simple-icon> Font Awesome</a>\n<br class='inline md:hidden'/><span class='hidden md:inline'>&emsp;</span>\n<a href='https://simpleicons.org/'><rock-band-simple-icon icon='simpleicons'></rock-band-simple-icon> Simple Icons</a>\n\n## Hosting\n\n<a href='https://github.com/' class='text-2xl font-light'><rock-band-simple-icon icon='github'></rock-band-simple-icon> GitHub</a>","dir":"/","path":"/credits","extension":".md","createdAt":"2022-01-28T17:59:06.377Z","updatedAt":"2022-01-28T17:59:06.377Z","meta":{"version":0,"revision":0,"created":1643392893306},"$loki":1},{"slug":"features","title":"Features","order":1,"date":"2021-08-12T19:34:09.000Z","toc":[{"id":"current-features","depth":2,"text":"Current Features"},{"id":"working-on-it","depth":2,"text":"Working On It"},{"id":"overwriteable-menus","depth":3,"text":"Overwriteable Menus"},{"id":"planned-features","depth":2,"text":"Planned Features"}],"body":{"type":"root","children":[{"type":"element","tag":"h2","props":{"id":"current-features"},"children":[{"type":"element","tag":"a","props":{"href":"#current-features","ariaHidden":"true","tabIndex":-1},"children":[{"type":"element","tag":"span","props":{"className":["icon","icon-link"]},"children":[]}]},{"type":"text","value":"Current Features"}]},{"type":"text","value":"\n"},{"type":"element","tag":"p","props":{},"children":[{"type":"text","value":"RockBand is a Nuxt component library that comes with:"}]},{"type":"text","value":"\n"},{"type":"element","tag":"ul","props":{},"children":[{"type":"text","value":"\n"},{"type":"element","tag":"li","props":{},"children":[{"type":"element","tag":"a","props":{"href":"https://image.nuxtjs.org/","rel":["nofollow","noopener","noreferrer"],"target":"_blank"},"children":[{"type":"text","value":"Nuxt Image"}]}]},{"type":"text","value":"\n"},{"type":"element","tag":"li","props":{},"children":[{"type":"element","tag":"a","props":{"href":"https://pugjs.org/api/getting-started.html","rel":["nofollow","noopener","noreferrer"],"target":"_blank"},"children":[{"type":"text","value":"Pug"}]}]},{"type":"text","value":"\n"},{"type":"element","tag":"li","props":{},"children":[{"type":"element","tag":"a","props":{"href":"https://tailwindcss.com/","rel":["nofollow","noopener","noreferrer"],"target":"_blank"},"children":[{"type":"text","value":"Tailwind CSS"}]},{"type":"text","value":" + "},{"type":"element","tag":"a","props":{"href":"https://github.com/tailwindlabs/tailwindcss-forms","rel":["nofollow","noopener","noreferrer"],"target":"_blank"},"children":[{"type":"text","value":"Tailwind CSS Forms"}]}]},{"type":"text","value":"\n"},{"type":"element","tag":"li","props":{},"children":[{"type":"element","tag":"a","props":{"href":"https://postcss.org/","rel":["nofollow","noopener","noreferrer"],"target":"_blank"},"children":[{"type":"text","value":"PostCSS"}]}]},{"type":"text","value":"\n"},{"type":"element","tag":"li","props":{},"children":[{"type":"element","tag":"a","props":{"href":"https://fontawesome.com/","rel":["nofollow","noopener","noreferrer"],"target":"_blank"},"children":[{"type":"text","value":"Font Awesome"}]}]},{"type":"text","value":"\n"},{"type":"element","tag":"li","props":{},"children":[{"type":"element","tag":"a","props":{"href":"https://simpleicons.org/","rel":["nofollow","noopener","noreferrer"],"target":"_blank"},"children":[{"type":"text","value":"Simple Icons"}]}]},{"type":"text","value":"\n"},{"type":"element","tag":"li","props":{},"children":[{"type":"element","tag":"a","props":{"href":"https://lodash.com/","rel":["nofollow","noopener","noreferrer"],"target":"_blank"},"children":[{"type":"text","value":"Lodash"}]}]},{"type":"text","value":"\n"},{"type":"element","tag":"li","props":{},"children":[{"type":"element","tag":"a","props":{"href":"https://github.com/thombruce/nuxt-taxonomies","rel":["nofollow","noopener","noreferrer"],"target":"_blank"},"children":[{"type":"text","value":"Nuxt Taxonomies"}]}]},{"type":"text","value":"\n"}]},{"type":"text","value":"\n"},{"type":"element","tag":"h2","props":{"id":"working-on-it"},"children":[{"type":"element","tag":"a","props":{"href":"#working-on-it","ariaHidden":"true","tabIndex":-1},"children":[{"type":"element","tag":"span","props":{"className":["icon","icon-link"]},"children":[]}]},{"type":"text","value":"Working On It"}]},{"type":"text","value":"\n"},{"type":"element","tag":"h3","props":{"id":"overwriteable-menus"},"children":[{"type":"element","tag":"a","props":{"href":"#overwriteable-menus","ariaHidden":"true","tabIndex":-1},"children":[{"type":"element","tag":"span","props":{"className":["icon","icon-link"]},"children":[]}]},{"type":"text","value":"Overwriteable Menus"}]},{"type":"text","value":"\n"},{"type":"element","tag":"p","props":{},"children":[{"type":"text","value":"At present, RockBand provides an automatic custom menu. The way in which to overwrite it, though, is to completely overwrite the component. I'd like to provide a menu customization option."}]},{"type":"text","value":"\n"},{"type":"element","tag":"p","props":{},"children":[{"type":"text","value":"This is also true of..."}]},{"type":"text","value":"\n"},{"type":"element","tag":"ul","props":{},"children":[{"type":"text","value":"\n"},{"type":"element","tag":"li","props":{},"children":[{"type":"text","value":"The footer; currently I override this to provide a list of social links and a custom copyright notice, each of which might be better served in config"}]},{"type":"text","value":"\n"},{"type":"element","tag":"li","props":{},"children":[{"type":"text","value":"The (classic) header; if I want to customise my header title at all (custom size, font, image, etc.) I currently override a deeply nested component"}]},{"type":"text","value":"\n"}]},{"type":"text","value":"\n"},{"type":"element","tag":"p","props":{},"children":[{"type":"text","value":"Where it makes sense, some of these values could be moved into "},{"type":"element","tag":"code","props":{},"children":[{"type":"text","value":"rockband.config.js"}]},{"type":"text","value":", a file I use elsewhere but that RockBand isn't yet aware of the existence of. And where it doesn't make sense, or as a workaround in the meantime, there could perhaps be components that are "},{"type":"element","tag":"em","props":{},"children":[{"type":"text","value":"meant"}]},{"type":"text","value":" to be overwritten. These should not be deeply nested, and they may borrow structural logic from Vue Chartjs which uses extendible components (I extend one of these in another project here: "},{"type":"element","tag":"a","props":{"href":"https://github.com/thombruce/vue-playfair/blob/main/src/components/BarChart.vue","rel":["nofollow","noopener","noreferrer"],"target":"_blank"},"children":[{"type":"text","value":"https://github.com/thombruce/vue-playfair/blob/main/src/components/BarChart.vue"}]},{"type":"text","value":")"}]},{"type":"text","value":"\n"},{"type":"element","tag":"h2","props":{"id":"planned-features"},"children":[{"type":"element","tag":"a","props":{"href":"#planned-features","ariaHidden":"true","tabIndex":-1},"children":[{"type":"element","tag":"span","props":{"className":["icon","icon-link"]},"children":[]}]},{"type":"text","value":"Planned Features"}]},{"type":"text","value":"\n"},{"type":"element","tag":"p","props":{},"children":[{"type":"text","value":"Nuxt 3 promises to make Nuxt even more powerful. In particular, RockBand is looking forwards to integrating the "},{"type":"element","tag":"a","props":{"href":"https://github.com/nuxt/rfcs/issues/30","rel":["nofollow","noopener","noreferrer"],"target":"_blank"},"children":[{"type":"text","value":"pluggable child apps API"}]},{"type":"text","value":" which could make RockBand a drop-in and go solution - no need to add a few pages to your Nuxt app anymore, RockBand would provide! A partial solution for this is offered by the Nuxt 2 plugin, "},{"type":"element","tag":"a","props":{"href":"https://github.com/nuxt-community/nuxt-extend","rel":["nofollow","noopener","noreferrer"],"target":"_blank"},"children":[{"type":"text","value":"nuxt-extend"}]},{"type":"text","value":"; the plugin does not support automatic integration of "},{"type":"element","tag":"code","props":{},"children":[{"type":"text","value":"pages/"}]},{"type":"text","value":" or "},{"type":"element","tag":"code","props":{},"children":[{"type":"text","value":"store/"}]},{"type":"text","value":" directories."}]},{"type":"text","value":"\n"},{"type":"element","tag":"p","props":{},"children":[{"type":"text","value":"Nuxt 3 also promises to include a "},{"type":"element","tag":"code","props":{},"children":[{"type":"text","value":"<Portal>"}]},{"type":"text","value":" component: "},{"type":"element","tag":"a","props":{"href":"https://github.com/nuxt/nuxt.js/issues/190#issuecomment-734239175","rel":["nofollow","noopener","noreferrer"],"target":"_blank"},"children":[{"type":"text","value":"https://github.com/nuxt/nuxt.js/issues/190#issuecomment-734239175"}]},{"type":"text","value":" This would enable the layout templates to expose \"portals\" into which deeply nested page or component templates could inject dynamic content. An existing solution for Vue 2 is the "},{"type":"element","tag":"a","props":{"href":"https://github.com/LinusBorg/portal-vue","rel":["nofollow","noopener","noreferrer"],"target":"_blank"},"children":[{"type":"text","value":"PortalVue"}]},{"type":"text","value":" plugin."}]}]},"text":"\n## Current Features\n\nRockBand is a Nuxt component library that comes with:\n\n- [Nuxt Image](https://image.nuxtjs.org/)\n- [Pug](https://pugjs.org/api/getting-started.html)\n- [Tailwind CSS](https://tailwindcss.com/) + [Tailwind CSS Forms](https://github.com/tailwindlabs/tailwindcss-forms)\n- [PostCSS](https://postcss.org/)\n- [Font Awesome](https://fontawesome.com/)\n- [Simple Icons](https://simpleicons.org/)\n- [Lodash](https://lodash.com/)\n- [Nuxt Taxonomies](https://github.com/thombruce/nuxt-taxonomies)\n\n## Working On It\n\n### Overwriteable Menus\n\nAt present, RockBand provides an automatic custom menu. The way in which to overwrite it, though, is to completely overwrite the component. I'd like to provide a menu customization option.\n\nThis is also true of...\n\n- The footer; currently I override this to provide a list of social links and a custom copyright notice, each of which might be better served in config\n- The (classic) header; if I want to customise my header title at all (custom size, font, image, etc.) I currently override a deeply nested component\n\nWhere it makes sense, some of these values could be moved into `rockband.config.js`, a file I use elsewhere but that RockBand isn't yet aware of the existence of. And where it doesn't make sense, or as a workaround in the meantime, there could perhaps be components that are _meant_ to be overwritten. These should not be deeply nested, and they may borrow structural logic from Vue Chartjs which uses extendible components (I extend one of these in another project here: https://github.com/thombruce/vue-playfair/blob/main/src/components/BarChart.vue)\n\n## Planned Features\n\nNuxt 3 promises to make Nuxt even more powerful. In particular, RockBand is looking forwards to integrating the [pluggable child apps API](https://github.com/nuxt/rfcs/issues/30) which could make RockBand a drop-in and go solution - no need to add a few pages to your Nuxt app anymore, RockBand would provide! A partial solution for this is offered by the Nuxt 2 plugin, [nuxt-extend](https://github.com/nuxt-community/nuxt-extend); the plugin does not support automatic integration of `pages/` or `store/` directories.\n\nNuxt 3 also promises to include a `<Portal>` component: https://github.com/nuxt/nuxt.js/issues/190#issuecomment-734239175 This would enable the layout templates to expose \"portals\" into which deeply nested page or component templates could inject dynamic content. An existing solution for Vue 2 is the [PortalVue](https://github.com/LinusBorg/portal-vue) plugin.","dir":"/","path":"/features","extension":".md","createdAt":"2022-01-28T17:59:06.377Z","updatedAt":"2022-01-28T17:59:06.377Z","meta":{"version":0,"revision":0,"created":1643392893356},"$loki":2},{"slug":"setlist","title":"Set List","date":"2022-01-23T15:17:52.000Z","toc":[{"id":"vue","depth":2,"text":"Vue"},{"id":"nuxt","depth":2,"text":"Nuxt"}],"body":{"type":"root","children":[{"type":"element","tag":"h2","props":{"id":"vue"},"children":[{"type":"element","tag":"a","props":{"ariaHidden":"true","href":"#vue","tabIndex":-1},"children":[{"type":"element","tag":"span","props":{"className":["icon","icon-link"]},"children":[]}]},{"type":"text","value":"Vue"}]},{"type":"text","value":"\n"},{"type":"element","tag":"ul","props":{},"children":[{"type":"text","value":"\n"},{"type":"element","tag":"li","props":{},"children":[{"type":"text","value":"Vue"}]},{"type":"text","value":"\n"},{"type":"element","tag":"li","props":{},"children":[{"type":"text","value":"Vue Meta"}]},{"type":"text","value":"\n"},{"type":"element","tag":"li","props":{},"children":[{"type":"text","value":"Tailwind CSS + Forms + Typography"}]},{"type":"text","value":"\n"},{"type":"element","tag":"li","props":{},"children":[{"type":"text","value":"Pug"}]},{"type":"text","value":"\n"},{"type":"element","tag":"li","props":{},"children":[{"type":"text","value":"PostCSS"}]},{"type":"text","value":"\n"},{"type":"element","tag":"li","props":{},"children":[{"type":"text","value":"Luxon"}]},{"type":"text","value":"\n"},{"type":"element","tag":"li","props":{},"children":[{"type":"text","value":"Lodash"}]},{"type":"text","value":"\n"},{"type":"element","tag":"li","props":{},"children":[{"type":"text","value":"Autoprefixer"}]},{"type":"text","value":"\n"},{"type":"element","tag":"li","props":{},"children":[{"type":"text","value":"Font Awesome"}]},{"type":"text","value":"\n"}]},{"type":"text","value":"\n"},{"type":"element","tag":"h2","props":{"id":"nuxt"},"children":[{"type":"element","tag":"a","props":{"ariaHidden":"true","href":"#nuxt","tabIndex":-1},"children":[{"type":"element","tag":"span","props":{"className":["icon","icon-link"]},"children":[]}]},{"type":"text","value":"Nuxt"}]},{"type":"text","value":"\n"},{"type":"element","tag":"ul","props":{},"children":[{"type":"text","value":"\n"},{"type":"element","tag":"li","props":{},"children":[{"type":"text","value":"Nuxt Image"}]},{"type":"text","value":"\n"},{"type":"element","tag":"li","props":{},"children":[{"type":"text","value":"Nuxt Color Mode"}]},{"type":"text","value":"\n"},{"type":"element","tag":"li","props":{},"children":[{"type":"text","value":"Nuxt Taxonomies"}]},{"type":"text","value":"\n"},{"type":"element","tag":"li","props":{},"children":[{"type":"text","value":"Simple Icons"}]},{"type":"text","value":"\n"},{"type":"element","tag":"li","props":{},"children":[{"type":"element","tag":"em","props":{},"children":[{"type":"text","value":"Supports Nuxt Content (installed separately)"}]}]},{"type":"text","value":"\n"}]}]},"text":"\n## Vue\n\n- Vue\n- Vue Meta\n- Tailwind CSS + Forms + Typography\n- Pug\n- PostCSS\n- Luxon\n- Lodash\n- Autoprefixer\n- Font Awesome\n\n## Nuxt\n\n- Nuxt Image\n- Nuxt Color Mode\n- Nuxt Taxonomies\n- Simple Icons\n- _Supports Nuxt Content (installed separately)_\n","dir":"/","path":"/setlist","extension":".md","createdAt":"2022-01-28T17:59:06.377Z","updatedAt":"2022-01-28T17:59:06.381Z","meta":{"version":0,"revision":0,"created":1643392893382},"$loki":3},{"slug":"breadcrumbs","title":"Breadcrumbs","date":"2021-08-12T19:34:11.000Z","toc":[],"body":{"type":"root","children":[{"type":"element","tag":"p","props":{},"children":[{"type":"text","value":"TODO"}]}]},"text":"\nTODO","dir":"/components","path":"/components/breadcrumbs","extension":".md","createdAt":"2022-01-28T17:59:06.377Z","updatedAt":"2022-01-28T17:59:06.377Z","meta":{"version":0,"revision":0,"created":1643392893397},"$loki":4},{"slug":"configuration","title":"Configuration","date":"2021-08-14T19:34:09.000Z","toc":[],"body":{"type":"root","children":[{"type":"element","tag":"p","props":{},"children":[{"type":"text","value":"TODO"}]},{"type":"text","value":"\n"},{"type":"element","tag":"p","props":{},"children":[{"type":"text","value":"For the time being, I've picked out two commits as reference for the installation and configuration of RockBand."}]},{"type":"text","value":"\n"},{"type":"element","tag":"p","props":{},"children":[{"type":"element","tag":"strong","props":{},"children":[{"type":"text","value":"Installation:"}]},{"type":"text","value":" "},{"type":"element","tag":"a","props":{"href":"https://github.com/thombruce/ordahhh/commit/e02e3664276e5973fa731baf35d4ecbbf32d4ffe","rel":["nofollow","noopener","noreferrer"],"target":"_blank"},"children":[{"type":"text","value":"https://github.com/thombruce/ordahhh/commit/e02e3664276e5973fa731baf35d4ecbbf32d4ffe"}]}]},{"type":"text","value":"\n"},{"type":"element","tag":"p","props":{},"children":[{"type":"text","value":"The installation commit runs "},{"type":"element","tag":"code","props":{},"children":[{"type":"text","value":"yarn add [source] --dev"}]},{"type":"text","value":" to add the RockBand dev dependency, and manually references "},{"type":"element","tag":"code","props":{},"children":[{"type":"text","value":"'@rockband/vue'"}]},{"type":"text","value":" in Nuxt's config file. It also adds three page templates, and removes the default components and page generated by Nuxt."}]},{"type":"text","value":"\n"},{"type":"element","tag":"p","props":{},"children":[{"type":"element","tag":"strong","props":{},"children":[{"type":"text","value":"Configuration:"}]},{"type":"text","value":" "},{"type":"element","tag":"a","props":{"href":"https://github.com/thombruce/ordahhh/commit/b71754fdc73cdc8212a7b9828b977a79310a104d","rel":["nofollow","noopener","noreferrer"],"target":"_blank"},"children":[{"type":"text","value":"https://github.com/thombruce/ordahhh/commit/b71754fdc73cdc8212a7b9828b977a79310a104d"}]}]},{"type":"text","value":"\n"},{"type":"element","tag":"p","props":{},"children":[{"type":"text","value":"This configuration commit does a bit more. It adds "},{"type":"element","tag":"code","props":{},"children":[{"type":"text","value":"tnt.config.js"}]},{"type":"text","value":", "},{"type":"element","tag":"code","props":{},"children":[{"type":"text","value":"tailwind.config.js"}]},{"type":"text","value":", "},{"type":"element","tag":"code","props":{},"children":[{"type":"text","value":"nuxt.feed.js"}]},{"type":"text","value":" and a default fallback image to the static directory with ideal dimensions for OpenGraph (1920x1080). It makes numerous changes to "},{"type":"element","tag":"code","props":{},"children":[{"type":"text","value":"nuxt.config.js"}]},{"type":"text","value":" in order to utilize the new files properly. "},{"type":"element","tag":"em","props":{},"children":[{"type":"text","value":"This is a bit cumbersome. In future and with the exception of the tailwind config file, I would like to constrain modifications to a single file (maybe two: "},{"type":"element","tag":"code","props":{},"children":[{"type":"text","value":"tnt.config.js"}]},{"type":"text","value":" and "},{"type":"element","tag":"code","props":{},"children":[{"type":"text","value":"tnt.feed.js"}]},{"type":"text","value":") and have the module itself do the work to merge that file with others."}]}]},{"type":"text","value":"\n"},{"type":"element","tag":"p","props":{},"children":[{"type":"element","tag":"em","props":{},"children":[{"type":"text","value":"Note: I also a deploy workflow to build the site on GitHub's CI: "},{"type":"element","tag":"a","props":{"href":"https://github.com/thombruce/ordahhh/commit/8e980c081dd420c74b0de9b15225130a4917cf6c","rel":["nofollow","noopener","noreferrer"],"target":"_blank"},"children":[{"type":"text","value":"https://github.com/thombruce/ordahhh/commit/8e980c081dd420c74b0de9b15225130a4917cf6c"}]}]}]}]},"text":"\nTODO\n\nFor the time being, I've picked out two commits as reference for the installation and configuration of RockBand.\n\n**Installation:** https://github.com/thombruce/ordahhh/commit/e02e3664276e5973fa731baf35d4ecbbf32d4ffe\n\nThe installation commit runs `yarn add [source] --dev` to add the RockBand dev dependency, and manually references `'@rockband/vue'` in Nuxt's config file. It also adds three page templates, and removes the default components and page generated by Nuxt.\n\n**Configuration:** https://github.com/thombruce/ordahhh/commit/b71754fdc73cdc8212a7b9828b977a79310a104d\n\nThis configuration commit does a bit more. It adds `tnt.config.js`, `tailwind.config.js`, `nuxt.feed.js` and a default fallback image to the static directory with ideal dimensions for OpenGraph (1920x1080). It makes numerous changes to `nuxt.config.js` in order to utilize the new files properly. _This is a bit cumbersome. In future and with the exception of the tailwind config file, I would like to constrain modifications to a single file (maybe two: `tnt.config.js` and `tnt.feed.js`) and have the module itself do the work to merge that file with others._\n\n_Note: I also a deploy workflow to build the site on GitHub's CI: https://github.com/thombruce/ordahhh/commit/8e980c081dd420c74b0de9b15225130a4917cf6c_","dir":"/getting-started","path":"/getting-started/configuration","extension":".md","createdAt":"2022-01-28T17:59:06.377Z","updatedAt":"2022-01-28T17:59:06.377Z","meta":{"version":0,"revision":0,"created":1643392893405},"$loki":5},{"slug":"installation","title":"Installation","date":"2021-07-31T19:34:09.000Z","toc":[{"id":"installation","depth":2,"text":"Installation"},{"id":"vue","depth":3,"text":"Vue"},{"id":"vue-cli","depth":3,"text":"Vue CLI"},{"id":"nuxt","depth":3,"text":"Nuxt"},{"id":"setup","depth":2,"text":"Setup"},{"id":"overwrite-default-styles","depth":2,"text":"Overwrite Default Styles"}],"body":{"type":"root","children":[{"type":"element","tag":"h2","props":{"id":"installation"},"children":[{"type":"element","tag":"a","props":{"href":"#installation","ariaHidden":"true","tabIndex":-1},"children":[{"type":"element","tag":"span","props":{"className":["icon","icon-link"]},"children":[]}]},{"type":"text","value":"Installation"}]},{"type":"text","value":"\n"},{"type":"element","tag":"h3","props":{"id":"vue"},"children":[{"type":"element","tag":"a","props":{"href":"#vue","ariaHidden":"true","tabIndex":-1},"children":[{"type":"element","tag":"span","props":{"className":["icon","icon-link"]},"children":[]}]},{"type":"text","value":"Vue"}]},{"type":"text","value":"\n"},{"type":"element","tag":"div","props":{"className":["nuxt-content-highlight"]},"children":[{"type":"element","tag":"pre","props":{},"children":[{"type":"element","tag":"code","props":{"className":["hljs","sh"]},"children":[{"type":"text","value":"yarn add --dev @rockband/vue\n"}]}]}]},{"type":"text","value":"\n"},{"type":"element","tag":"h3","props":{"id":"vue-cli"},"children":[{"type":"element","tag":"a","props":{"href":"#vue-cli","ariaHidden":"true","tabIndex":-1},"children":[{"type":"element","tag":"span","props":{"className":["icon","icon-link"]},"children":[]}]},{"type":"text","value":"Vue CLI"}]},{"type":"text","value":"\n"},{"type":"element","tag":"p","props":{},"children":[{"type":"text","value":"Add RockBand to your project and run the initializer:"}]},{"type":"text","value":"\n"},{"type":"element","tag":"div","props":{"className":["nuxt-content-highlight"]},"children":[{"type":"element","tag":"pre","props":{},"children":[{"type":"element","tag":"code","props":{"className":["hljs","sh"]},"children":[{"type":"text","value":"vue add @rockband/vue\n"}]}]}]},{"type":"text","value":"\n"},{"type":"element","tag":"h3","props":{"id":"nuxt"},"children":[{"type":"element","tag":"a","props":{"href":"#nuxt","ariaHidden":"true","tabIndex":-1},"children":[{"type":"element","tag":"span","props":{"className":["icon","icon-link"]},"children":[]}]},{"type":"text","value":"Nuxt"}]},{"type":"text","value":"\n"},{"type":"element","tag":"p","props":{},"children":[{"type":"text","value":"Add RockBand to your project:"}]},{"type":"text","value":"\n"},{"type":"element","tag":"div","props":{"className":["nuxt-content-highlight"]},"children":[{"type":"element","tag":"pre","props":{},"children":[{"type":"element","tag":"code","props":{"className":["hljs","sh"]},"children":[{"type":"text","value":"yarn add --dev @rockband/nuxt\n"}]}]}]},{"type":"text","value":"\n"},{"type":"element","tag":"p","props":{},"children":[{"type":"text","value":"Add RockBand to buildModules in "},{"type":"element","tag":"code","props":{},"children":[{"type":"text","value":"nuxt.config.js"}]},{"type":"text","value":":"}]},{"type":"text","value":"\n"},{"type":"element","tag":"div","props":{"className":["nuxt-content-highlight"]},"children":[{"type":"element","tag":"pre","props":{},"children":[{"type":"element","tag":"code","props":{"className":["hljs","js"]},"children":[{"type":"element","tag":"span","props":{"className":["hljs-attr"]},"children":[{"type":"text","value":"buildModules"}]},{"type":"text","value":": [\n  "},{"type":"element","tag":"span","props":{"className":["hljs-string"]},"children":[{"type":"text","value":"'@rockband/nuxt'"}]},{"type":"text","value":"\n]\n"}]}]}]},{"type":"text","value":"\n"},{"type":"element","tag":"h2","props":{"id":"setup"},"children":[{"type":"element","tag":"a","props":{"href":"#setup","ariaHidden":"true","tabIndex":-1},"children":[{"type":"element","tag":"span","props":{"className":["icon","icon-link"]},"children":[]}]},{"type":"text","value":"Setup"}]},{"type":"text","value":"\n"},{"type":"element","tag":"p","props":{},"children":[{"type":"text","value":"RockBand comes with a default layout, but you'll still need to create your own pages in Nuxt. A good place to look at how this is done is the pages directory on this very project: "},{"type":"element","tag":"a","props":{"href":"https://github.com/thombruce/rockband/","rel":["nofollow","noopener","noreferrer"],"target":"_blank"},"children":[{"type":"text","value":"https://github.com/thombruce/rockband/"}]},{"type":"text","value":" You can copy these to your own project, modifying their names and contents as necessary - for example by changing any instance of 'docs' to 'blog'."}]},{"type":"text","value":"\n"},{"type":"element","tag":"h2","props":{"id":"overwrite-default-styles"},"children":[{"type":"element","tag":"a","props":{"href":"#overwrite-default-styles","ariaHidden":"true","tabIndex":-1},"children":[{"type":"element","tag":"span","props":{"className":["icon","icon-link"]},"children":[]}]},{"type":"text","value":"Overwrite Default Styles"}]},{"type":"text","value":"\n"},{"type":"element","tag":"p","props":{},"children":[{"type":"text","value":"Create a CSS file at "},{"type":"element","tag":"code","props":{},"children":[{"type":"text","value":"assets/css/rockband.css"}]},{"type":"text","value":" and import "},{"type":"element","tag":"code","props":{},"children":[{"type":"text","value":"@rockband/vue"}]},{"type":"text","value":":"}]},{"type":"text","value":"\n"},{"type":"element","tag":"div","props":{"className":["nuxt-content-highlight"]},"children":[{"type":"element","tag":"pre","props":{},"children":[{"type":"element","tag":"code","props":{"className":["hljs","css"]},"children":[{"type":"element","tag":"span","props":{"className":["hljs-keyword"]},"children":[{"type":"text","value":"@import"}]},{"type":"text","value":" "},{"type":"element","tag":"span","props":{"className":["hljs-string"]},"children":[{"type":"text","value":"\"@rockband/vue\""}]},{"type":"text","value":";\n\n"},{"type":"element","tag":"span","props":{"className":["hljs-comment"]},"children":[{"type":"text","value":"/* Declare your styles or local imports here. */"}]},{"type":"text","value":"\n"}]}]}]},{"type":"text","value":"\n"},{"type":"element","tag":"p","props":{},"children":[{"type":"text","value":"RockBand comes with Tailwind CSS and PostCSS; you can count on both of them working for this file and its imports. And of course, you can just write plain old CSS."}]},{"type":"text","value":"\n"},{"type":"element","tag":"p","props":{},"children":[{"type":"text","value":"You can also configure "},{"type":"element","tag":"code","props":{},"children":[{"type":"text","value":"tailwind.config.js"}]},{"type":"text","value":" following their docs. Apart from the "},{"type":"element","tag":"code","props":{},"children":[{"type":"text","value":"rockband.css"}]},{"type":"text","value":" file, it's just like any other Tailwind installation."}]}]},"text":"\n## Installation\n\n### Vue\n\n```sh\nyarn add --dev @rockband/vue\n```\n\n### Vue CLI\n\nAdd RockBand to your project and run the initializer:\n\n```sh\nvue add @rockband/vue\n```\n\n### Nuxt\n\nAdd RockBand to your project:\n\n```sh\nyarn add --dev @rockband/nuxt\n```\n\nAdd RockBand to buildModules in `nuxt.config.js`:\n\n```js\nbuildModules: [\n  '@rockband/nuxt'\n]\n```\n\n## Setup\n\nRockBand comes with a default layout, but you'll still need to create your own pages in Nuxt. A good place to look at how this is done is the pages directory on this very project: https://github.com/thombruce/rockband/ You can copy these to your own project, modifying their names and contents as necessary - for example by changing any instance of 'docs' to 'blog'.\n\n## Overwrite Default Styles\n\nCreate a CSS file at `assets/css/rockband.css` and import `@rockband/vue`:\n\n```css\n@import \"@rockband/vue\";\n\n/* Declare your styles or local imports here. */\n```\n\nRockBand comes with Tailwind CSS and PostCSS; you can count on both of them working for this file and its imports. And of course, you can just write plain old CSS.\n\nYou can also configure `tailwind.config.js` following their docs. Apart from the `rockband.css` file, it's just like any other Tailwind installation.","dir":"/getting-started","path":"/getting-started/installation","extension":".md","createdAt":"2022-01-28T17:59:06.377Z","updatedAt":"2022-01-28T17:59:06.377Z","meta":{"version":0,"revision":0,"created":1643392893424},"$loki":6}],"idIndex":[1,2,3,4,5,6],"maxId":6,"_dirty":true,"_nestedProperties":[],"transactional":false,"asyncListeners":false,"disableMeta":false,"disableChangesApi":true,"disableDeltaChangesApi":true,"cloneObjects":false,"cloneMethod":"deep","changes":[],"_fullTextSearch":{"ii":{"title":{"_store":true,"_optimizeChanges":true,"docCount":6,"docStore":[[0,{"fieldLength":1}],[1,{"fieldLength":1}],[2,{"fieldLength":2}],[3,{"fieldLength":1}],[4,{"fieldLength":1}],[5,{"fieldLength":1}]],"totalFieldLength":7,"root":{"k":[99,102,115,108,98,105],"v":[{"k":[114,111],"v":[{"k":[101],"v":[{"k":[100],"v":[{"k":[105],"v":[{"k":[116],"v":[{"k":[115],"v":[{"d":{"df":1,"dc":[[0,1]]}}]}]}]}]}]},{"k":[110],"v":[{"k":[102],"v":[{"k":[105],"v":[{"k":[103],"v":[{"k":[117],"v":[{"k":[114],"v":[{"k":[97],"v":[{"k":[116],"v":[{"k":[105],"v":[{"k":[111],"v":[{"k":[110],"v":[{"d":{"df":1,"dc":[[4,1]]}}]}]}]}]}]}]}]}]}]}]}]}]},{"k":[101],"v":[{"k":[97],"v":[{"k":[116],"v":[{"k":[117],"v":[{"k":[114],"v":[{"k":[101],"v":[{"k":[115],"v":[{"d":{"df":1,"dc":[[1,1]]}}]}]}]}]}]}]}]},{"k":[101],"v":[{"k":[116],"v":[{"d":{"df":1,"dc":[[2,1]]}}]}]},{"k":[105],"v":[{"k":[115],"v":[{"k":[116],"v":[{"d":{"df":1,"dc":[[2,1]]}}]}]}]},{"k":[114],"v":[{"k":[101],"v":[{"k":[97],"v":[{"k":[100],"v":[{"k":[99],"v":[{"k":[114],"v":[{"k":[117],"v":[{"k":[109],"v":[{"k":[98],"v":[{"k":[115],"v":[{"d":{"df":1,"dc":[[3,1]]}}]}]}]}]}]}]}]}]}]}]},{"k":[110],"v":[{"k":[115],"v":[{"k":[116],"v":[{"k":[97],"v":[{"k":[108],"v":[{"k":[108],"v":[{"k":[97],"v":[{"k":[116],"v":[{"k":[105],"v":[{"k":[111],"v":[{"k":[110],"v":[{"d":{"df":1,"dc":[[5,1]]}}]}]}]}]}]}]}]}]}]}]}]}]}},"description":{"_store":true,"_optimizeChanges":true,"docCount":1,"docStore":[[0,{"fieldLength":6}]],"totalFieldLength":6,"root":{"k":[112,97,109,117,98,114],"v":[{"k":[97],"v":[{"k":[99],"v":[{"k":[107],"v":[{"k":[97],"v":[{"k":[103],"v":[{"k":[101],"v":[{"k":[115],"v":[{"d":{"df":1,"dc":[[0,1]]}}]}]}]}]}]}]}]},{"k":[110],"v":[{"k":[100],"v":[{"d":{"df":1,"dc":[[0,1]]}}]}]},{"k":[101],"v":[{"k":[100],"v":[{"k":[105],"v":[{"k":[97],"v":[{"d":{"df":1,"dc":[[0,1]]}}]}]}]}]},{"k":[115],"v":[{"k":[101],"v":[{"k":[100],"v":[{"d":{"df":1,"dc":[[0,1]]}}]}]}]},{"k":[121],"v":[{"d":{"df":1,"dc":[[0,1]]}}]},{"k":[111],"v":[{"k":[99],"v":[{"k":[107],"v":[{"k":[98],"v":[{"k":[97],"v":[{"k":[110],"v":[{"k":[100],"v":[{"k":[46],"v":[{"d":{"df":1,"dc":[[0,1]]}}]}]}]}]}]}]}]}]}]}},"slug":{"_store":true,"_optimizeChanges":true,"docCount":6,"docStore":[[0,{"fieldLength":1}],[1,{"fieldLength":1}],[2,{"fieldLength":1}],[3,{"fieldLength":1}],[4,{"fieldLength":1}],[5,{"fieldLength":1}]],"totalFieldLength":6,"root":{"k":[99,102,115,98,105],"v":[{"k":[114,111],"v":[{"k":[101],"v":[{"k":[100],"v":[{"k":[105],"v":[{"k":[116],"v":[{"k":[115],"v":[{"d":{"df":1,"dc":[[0,1]]}}]}]}]}]}]},{"k":[110],"v":[{"k":[102],"v":[{"k":[105],"v":[{"k":[103],"v":[{"k":[117],"v":[{"k":[114],"v":[{"k":[97],"v":[{"k":[116],"v":[{"k":[105],"v":[{"k":[111],"v":[{"k":[110],"v":[{"d":{"df":1,"dc":[[4,1]]}}]}]}]}]}]}]}]}]}]}]}]}]},{"k":[101],"v":[{"k":[97],"v":[{"k":[116],"v":[{"k":[117],"v":[{"k":[114],"v":[{"k":[101],"v":[{"k":[115],"v":[{"d":{"df":1,"dc":[[1,1]]}}]}]}]}]}]}]}]},{"k":[101],"v":[{"k":[116],"v":[{"k":[108],"v":[{"k":[105],"v":[{"k":[115],"v":[{"k":[116],"v":[{"d":{"df":1,"dc":[[2,1]]}}]}]}]}]}]}]},{"k":[114],"v":[{"k":[101],"v":[{"k":[97],"v":[{"k":[100],"v":[{"k":[99],"v":[{"k":[114],"v":[{"k":[117],"v":[{"k":[109],"v":[{"k":[98],"v":[{"k":[115],"v":[{"d":{"df":1,"dc":[[3,1]]}}]}]}]}]}]}]}]}]}]}]},{"k":[110],"v":[{"k":[115],"v":[{"k":[116],"v":[{"k":[97],"v":[{"k":[108],"v":[{"k":[108],"v":[{"k":[97],"v":[{"k":[116],"v":[{"k":[105],"v":[{"k":[111],"v":[{"k":[110],"v":[{"d":{"df":1,"dc":[[5,1]]}}]}]}]}]}]}]}]}]}]}]}]}]}},"text":{"_store":true,"_optimizeChanges":true,"docCount":6,"docStore":[[0,{"fieldLength":55}],[1,{"fieldLength":330}],[2,{"fieldLength":48}],[3,{"fieldLength":1}],[4,{"fieldLength":161}],[5,{"fieldLength":193}]],"totalFieldLength":788,"root":{"k":[35,119,60,104,99,102,98,105,110,109,116,97,115,103,114,108,45,91,43,111,112,101,40,100,118,96,117,121,95,51,50,34,42,64,39,93,47,106],"v":[{"k":[35],"v":[{"d":{"df":4,"dc":[[0,4],[1,3],[2,2],[5,3]]},"k":[35],"v":[{"d":{"df":2,"dc":[[1,1],[5,3]]}}]}]},{"k":[114,105,111,97,104],"v":[{"k":[105],"v":[{"k":[116],"v":[{"k":[101],"v":[{"d":{"df":1,"dc":[[5,1]]},"k":[114],"v":[{"k":[47],"v":[{"k":[100],"v":[{"k":[101],"v":[{"k":[118],"v":[{"k":[101],"v":[{"k":[108],"v":[{"k":[111],"v":[{"k":[112],"v":[{"k":[101],"v":[{"k":[114],"v":[{"d":{"df":1,"dc":[[0,1]]}}]}]}]}]}]}]}]}]}]}]}]}]}]}]},{"k":[116],"v":[{"k":[104],"v":[{"d":{"df":3,"dc":[[0,1],[4,3],[5,2]]},"k":[58],"v":[{"d":{"df":1,"dc":[[1,1]]}}]}]}]},{"k":[114,117],"v":[{"k":[107],"v":[{"d":{"df":1,"dc":[[4,1]]},"k":[105,97,102],"v":[{"k":[110],"v":[{"k":[103],"v":[{"d":{"df":2,"dc":[[1,1],[5,1]]}}]}]},{"k":[114],"v":[{"k":[111],"v":[{"k":[117],"v":[{"k":[110],"v":[{"k":[100],"v":[{"d":{"df":1,"dc":[[1,1]]}}]}]}]}]}]},{"k":[108],"v":[{"k":[111],"v":[{"k":[119],"v":[{"d":{"df":1,"dc":[[4,1]]}}]}]}]}]}]},{"k":[108],"v":[{"k":[100],"v":[{"d":{"df":2,"dc":[[1,2],[4,1]]}}]}]}]},{"k":[121,110],"v":[{"d":{"df":1,"dc":[[1,1]]}},{"k":[116],"v":[{"d":{"df":1,"dc":[[1,1]]}}]}]},{"k":[105,101],"v":[{"k":[99],"v":[{"k":[104],"v":[{"d":{"df":1,"dc":[[1,5]]}}]}]},{"k":[114],"v":[{"k":[101],"v":[{"d":{"df":1,"dc":[[1,2]]}}]}]}]}]},{"k":[97,98],"v":[{"d":{"df":1,"dc":[[0,6]]}},{"k":[114],"v":[{"d":{"df":1,"dc":[[0,2]]},"k":[47],"v":[{"k":[62],"v":[{"d":{"df":1,"dc":[[0,4]]}}]}]}]}]},{"k":[114,111,101,116,97],"v":[{"k":[101],"v":[{"k":[102],"v":[{"k":[61],"v":[{"k":[39],"v":[{"k":[104],"v":[{"k":[116],"v":[{"k":[116],"v":[{"k":[112],"v":[{"k":[115],"v":[{"k":[58],"v":[{"k":[47],"v":[{"k":[47],"v":[{"k":[116,110,102,115,103],"v":[{"k":[104,97],"v":[{"k":[111],"v":[{"k":[109],"v":[{"k":[98],"v":[{"k":[114],"v":[{"k":[117],"v":[{"k":[99],"v":[{"k":[101],"v":[{"k":[46],"v":[{"k":[99],"v":[{"k":[111],"v":[{"k":[109],"v":[{"k":[47],"v":[{"k":[39],"v":[{"d":{"df":1,"dc":[[0,1]]}}]}]}]}]}]}]}]}]}]}]}]}]}]},{"k":[105],"v":[{"k":[108],"v":[{"k":[119],"v":[{"k":[105],"v":[{"k":[110],"v":[{"k":[100],"v":[{"k":[99],"v":[{"k":[115],"v":[{"k":[115],"v":[{"k":[46],"v":[{"k":[99],"v":[{"k":[111],"v":[{"k":[109],"v":[{"k":[47],"v":[{"k":[39],"v":[{"d":{"df":1,"dc":[[0,1]]}}]}]}]}]}]}]}]}]}]}]}]}]}]}]}]}]},{"k":[117],"v":[{"k":[120],"v":[{"k":[116],"v":[{"k":[106],"v":[{"k":[115],"v":[{"k":[46],"v":[{"k":[111],"v":[{"k":[114],"v":[{"k":[103],"v":[{"k":[47],"v":[{"k":[39],"v":[{"d":{"df":1,"dc":[[0,1]]}}]}]}]}]}]}]}]}]}]}]}]},{"k":[111],"v":[{"k":[110],"v":[{"k":[116],"v":[{"k":[97],"v":[{"k":[119],"v":[{"k":[101],"v":[{"k":[115],"v":[{"k":[111],"v":[{"k":[109],"v":[{"k":[101],"v":[{"k":[46],"v":[{"k":[99],"v":[{"k":[111],"v":[{"k":[109],"v":[{"k":[47],"v":[{"k":[39],"v":[{"k":[62],"v":[{"k":[60],"v":[{"k":[114],"v":[{"k":[111],"v":[{"k":[99],"v":[{"k":[107],"v":[{"k":[45],"v":[{"k":[98],"v":[{"k":[97],"v":[{"k":[110],"v":[{"k":[100],"v":[{"k":[45],"v":[{"k":[115],"v":[{"k":[105],"v":[{"k":[109],"v":[{"k":[112],"v":[{"k":[108],"v":[{"k":[101],"v":[{"k":[45],"v":[{"k":[105],"v":[{"k":[99],"v":[{"k":[111],"v":[{"k":[110],"v":[{"d":{"df":1,"dc":[[0,1]]}}]}]}]}]}]}]}]}]}]}]}]}]}]}]}]}]}]}]}]}]}]}]}]}]}]}]}]}]}]}]}]}]}]}]}]}]}]}]}]},{"k":[105],"v":[{"k":[109],"v":[{"k":[112],"v":[{"k":[108],"v":[{"k":[101],"v":[{"k":[105],"v":[{"k":[99],"v":[{"k":[111],"v":[{"k":[110],"v":[{"k":[115],"v":[{"k":[46],"v":[{"k":[111],"v":[{"k":[114],"v":[{"k":[103],"v":[{"k":[47],"v":[{"k":[39],"v":[{"k":[62],"v":[{"k":[60],"v":[{"k":[114],"v":[{"k":[111],"v":[{"k":[99],"v":[{"k":[107],"v":[{"k":[45],"v":[{"k":[98],"v":[{"k":[97],"v":[{"k":[110],"v":[{"k":[100],"v":[{"k":[45],"v":[{"k":[115],"v":[{"k":[105],"v":[{"k":[109],"v":[{"k":[112],"v":[{"k":[108],"v":[{"k":[101],"v":[{"k":[45],"v":[{"k":[105],"v":[{"k":[99],"v":[{"k":[111],"v":[{"k":[110],"v":[{"d":{"df":1,"dc":[[0,1]]}}]}]}]}]}]}]}]}]}]}]}]}]}]}]}]}]}]}]}]}]}]}]}]}]}]}]}]}]}]}]}]}]}]}]}]}]}]}]}]},{"k":[105],"v":[{"k":[116],"v":[{"k":[104],"v":[{"k":[117],"v":[{"k":[98],"v":[{"k":[46],"v":[{"k":[99],"v":[{"k":[111],"v":[{"k":[109],"v":[{"k":[47],"v":[{"k":[39],"v":[{"d":{"df":1,"dc":[[0,1]]}}]}]}]}]}]}]}]}]}]}]}]}]}]}]}]}]}]}]}]}]}]}]}]}]},{"k":[115,119],"v":[{"k":[116],"v":[{"k":[105],"v":[{"k":[110],"v":[{"k":[103],"v":[{"d":{"df":1,"dc":[[0,1]]}}]}]}]}]},{"d":{"df":1,"dc":[[5,1]]}}]},{"k":[97,114],"v":[{"k":[100],"v":[{"k":[101],"v":[{"k":[114],"v":[{"d":{"df":1,"dc":[[1,1]]},"k":[59],"v":[{"d":{"df":1,"dc":[[1,1]]}}]}]}]}]},{"k":[101],"v":[{"k":[58,46],"v":[{"d":{"df":1,"dc":[[1,1]]}},{"d":{"df":1,"dc":[[5,1]]}}]}]}]},{"k":[116],"v":[{"k":[112],"v":[{"k":[115],"v":[{"k":[58],"v":[{"k":[47],"v":[{"k":[47],"v":[{"k":[103],"v":[{"k":[105],"v":[{"k":[116],"v":[{"k":[104],"v":[{"k":[117],"v":[{"k":[98],"v":[{"k":[46],"v":[{"k":[99],"v":[{"k":[111],"v":[{"k":[109],"v":[{"k":[47],"v":[{"k":[116,110],"v":[{"k":[104],"v":[{"k":[111],"v":[{"k":[109],"v":[{"k":[98],"v":[{"k":[114],"v":[{"k":[117],"v":[{"k":[99],"v":[{"k":[101],"v":[{"k":[47],"v":[{"k":[118,111,114],"v":[{"k":[117],"v":[{"k":[101],"v":[{"k":[45],"v":[{"k":[112],"v":[{"k":[108],"v":[{"k":[97],"v":[{"k":[121],"v":[{"k":[102],"v":[{"k":[97],"v":[{"k":[105],"v":[{"k":[114],"v":[{"k":[47],"v":[{"k":[98],"v":[{"k":[108],"v":[{"k":[111],"v":[{"k":[98],"v":[{"k":[47],"v":[{"k":[109],"v":[{"k":[97],"v":[{"k":[105],"v":[{"k":[110],"v":[{"k":[47],"v":[{"k":[115],"v":[{"k":[114],"v":[{"k":[99],"v":[{"k":[47],"v":[{"k":[99],"v":[{"k":[111],"v":[{"k":[109],"v":[{"k":[112],"v":[{"k":[111],"v":[{"k":[110],"v":[{"k":[101],"v":[{"k":[110],"v":[{"k":[116],"v":[{"k":[115],"v":[{"k":[47],"v":[{"k":[98],"v":[{"k":[97],"v":[{"k":[114],"v":[{"k":[99],"v":[{"k":[104],"v":[{"k":[97],"v":[{"k":[114],"v":[{"k":[116],"v":[{"k":[46],"v":[{"k":[118],"v":[{"k":[117],"v":[{"k":[101],"v":[{"k":[41],"v":[{"d":{"df":1,"dc":[[1,1]]}}]}]}]}]}]}]}]}]}]}]}]}]}]}]}]}]}]}]}]}]}]}]}]}]}]}]}]}]}]}]}]}]}]}]}]}]}]}]}]}]}]}]}]}]}]}]}]}]}]}]},{"k":[114],"v":[{"k":[100],"v":[{"k":[97],"v":[{"k":[104],"v":[{"k":[104],"v":[{"k":[104],"v":[{"k":[47],"v":[{"k":[99],"v":[{"k":[111],"v":[{"k":[109],"v":[{"k":[109],"v":[{"k":[105],"v":[{"k":[116],"v":[{"k":[47],"v":[{"k":[101,98,56],"v":[{"k":[48],"v":[{"k":[50],"v":[{"k":[101],"v":[{"k":[51],"v":[{"k":[54],"v":[{"k":[54],"v":[{"k":[52],"v":[{"k":[50],"v":[{"k":[55],"v":[{"k":[54],"v":[{"k":[101],"v":[{"k":[53],"v":[{"k":[57],"v":[{"k":[55],"v":[{"k":[51],"v":[{"k":[102],"v":[{"k":[97],"v":[{"k":[55],"v":[{"k":[51],"v":[{"k":[49],"v":[{"k":[98],"v":[{"k":[97],"v":[{"k":[102],"v":[{"k":[51],"v":[{"k":[53],"v":[{"k":[100],"v":[{"k":[52],"v":[{"k":[101],"v":[{"k":[99],"v":[{"k":[98],"v":[{"k":[98],"v":[{"k":[102],"v":[{"k":[51],"v":[{"k":[50],"v":[{"k":[100],"v":[{"k":[52],"v":[{"k":[102],"v":[{"k":[102],"v":[{"k":[101],"v":[{"d":{"df":1,"dc":[[4,1]]}}]}]}]}]}]}]}]}]}]}]}]}]}]}]}]}]}]}]}]}]}]}]}]}]}]}]}]}]}]}]}]}]}]}]}]}]}]}]}]},{"k":[55],"v":[{"k":[49],"v":[{"k":[55],"v":[{"k":[53],"v":[{"k":[52],"v":[{"k":[102],"v":[{"k":[100],"v":[{"k":[99],"v":[{"k":[55],"v":[{"k":[51],"v":[{"k":[99],"v":[{"k":[100],"v":[{"k":[99],"v":[{"k":[56],"v":[{"k":[50],"v":[{"k":[49],"v":[{"k":[50],"v":[{"k":[97],"v":[{"k":[55],"v":[{"k":[98],"v":[{"k":[57],"v":[{"k":[56],"v":[{"k":[50],"v":[{"k":[56],"v":[{"k":[98],"v":[{"k":[57],"v":[{"k":[55],"v":[{"k":[55],"v":[{"k":[97],"v":[{"k":[55],"v":[{"k":[57],"v":[{"k":[51],"v":[{"k":[49],"v":[{"k":[48],"v":[{"k":[97],"v":[{"k":[49],"v":[{"k":[48],"v":[{"k":[52],"v":[{"k":[100],"v":[{"d":{"df":1,"dc":[[4,1]]}}]}]}]}]}]}]}]}]}]}]}]}]}]}]}]}]}]}]}]}]}]}]}]}]}]}]}]}]}]}]}]}]}]}]}]}]}]}]}]},{"k":[101],"v":[{"k":[57],"v":[{"k":[56],"v":[{"k":[48],"v":[{"k":[99],"v":[{"k":[48],"v":[{"k":[56],"v":[{"k":[49],"v":[{"k":[100],"v":[{"k":[100],"v":[{"k":[52],"v":[{"k":[50],"v":[{"k":[48],"v":[{"k":[99],"v":[{"k":[55],"v":[{"k":[52],"v":[{"k":[98],"v":[{"k":[48],"v":[{"k":[100],"v":[{"k":[101],"v":[{"k":[57],"v":[{"k":[98],"v":[{"k":[49],"v":[{"k":[53],"v":[{"k":[50],"v":[{"k":[50],"v":[{"k":[53],"v":[{"k":[49],"v":[{"k":[51],"v":[{"k":[48],"v":[{"k":[97],"v":[{"k":[52],"v":[{"k":[57],"v":[{"k":[49],"v":[{"k":[55],"v":[{"k":[99],"v":[{"k":[102],"v":[{"k":[54],"v":[{"k":[99],"v":[{"k":[95],"v":[{"d":{"df":1,"dc":[[4,1]]}}]}]}]}]}]}]}]}]}]}]}]}]}]}]}]}]}]}]}]}]}]}]}]}]}]}]}]}]}]}]}]}]}]}]}]}]}]}]}]}]}]}]}]}]}]}]}]}]}]}]}]}]}]}]}]},{"k":[111],"v":[{"k":[99],"v":[{"k":[107],"v":[{"k":[98],"v":[{"k":[97],"v":[{"k":[110],"v":[{"k":[100],"v":[{"k":[47],"v":[{"d":{"df":1,"dc":[[5,1]]}}]}]}]}]}]}]}]}]}]}]}]}]}]}]}]}]}]}]},{"k":[117],"v":[{"k":[120],"v":[{"k":[116],"v":[{"k":[47],"v":[{"k":[110],"v":[{"k":[117],"v":[{"k":[120],"v":[{"k":[116],"v":[{"k":[46],"v":[{"k":[106],"v":[{"k":[115],"v":[{"k":[47],"v":[{"k":[105],"v":[{"k":[115],"v":[{"k":[115],"v":[{"k":[117],"v":[{"k":[101],"v":[{"k":[115],"v":[{"k":[47],"v":[{"k":[49],"v":[{"k":[57],"v":[{"k":[48],"v":[{"k":[35],"v":[{"k":[105],"v":[{"k":[115],"v":[{"k":[115],"v":[{"k":[117],"v":[{"k":[101],"v":[{"k":[99],"v":[{"k":[111],"v":[{"k":[109],"v":[{"k":[109],"v":[{"k":[101],"v":[{"k":[110],"v":[{"k":[116],"v":[{"k":[45],"v":[{"k":[55],"v":[{"k":[51],"v":[{"k":[52],"v":[{"k":[50],"v":[{"k":[51],"v":[{"k":[57],"v":[{"k":[49],"v":[{"k":[55],"v":[{"k":[53],"v":[{"d":{"df":1,"dc":[[1,1]]}}]}]}]}]}]}]}]}]}]}]}]}]}]}]}]}]}]}]}]}]}]}]}]}]}]}]}]}]}]}]}]}]}]}]}]}]}]}]}]}]}]}]}]}]}]}]}]}]}]}]}]}]}]}]}]}]}]}]}]}]}]}]}]},{"k":[118],"v":[{"k":[101],"v":[{"d":{"df":1,"dc":[[4,1]]}}]}]}]},{"k":[108,115,117,111,104,105,114,97],"v":[{"k":[97,105],"v":[{"k":[115],"v":[{"k":[115],"v":[{"k":[61],"v":[{"k":[39],"v":[{"k":[116,105,104],"v":[{"k":[101],"v":[{"k":[120],"v":[{"k":[116],"v":[{"k":[45],"v":[{"k":[51,50],"v":[{"k":[120],"v":[{"k":[108],"v":[{"d":{"df":1,"dc":[[0,1]]}}]}]},{"k":[120],"v":[{"k":[108],"v":[{"d":{"df":1,"dc":[[0,1]]},"k":[39],"v":[{"k":[62],"v":[{"k":[60],"v":[{"k":[114],"v":[{"k":[111],"v":[{"k":[99],"v":[{"k":[107],"v":[{"k":[45],"v":[{"k":[98],"v":[{"k":[97],"v":[{"k":[110],"v":[{"k":[100],"v":[{"k":[45],"v":[{"k":[115],"v":[{"k":[105],"v":[{"k":[109],"v":[{"k":[112],"v":[{"k":[108],"v":[{"k":[101],"v":[{"k":[45],"v":[{"k":[105],"v":[{"k":[99],"v":[{"k":[111],"v":[{"k":[110],"v":[{"d":{"df":1,"dc":[[0,2]]}}]}]}]}]}]}]}]}]}]}]}]}]}]}]}]}]}]}]}]}]}]}]}]}]}]}]}]}]}]}]}]},{"k":[110],"v":[{"k":[108],"v":[{"k":[105],"v":[{"k":[110],"v":[{"k":[101],"v":[{"d":{"df":1,"dc":[[0,2]]}}]}]}]}]}]},{"k":[105],"v":[{"k":[100],"v":[{"k":[100],"v":[{"k":[101],"v":[{"k":[110],"v":[{"d":{"df":1,"dc":[[0,2]]}}]}]}]}]}]}]}]}]}]}]},{"d":{"df":1,"dc":[[5,1]]}}]},{"k":[115],"v":[{"d":{"df":3,"dc":[[1,1],[2,1],[5,2]]},"k":[60,93,46],"v":[{"k":[47],"v":[{"k":[97],"v":[{"k":[62],"v":[{"d":{"df":1,"dc":[[0,1]]}}]}]}]},{"k":[40],"v":[{"k":[104],"v":[{"k":[116],"v":[{"k":[116],"v":[{"k":[112],"v":[{"k":[115],"v":[{"k":[58],"v":[{"k":[47],"v":[{"k":[47],"v":[{"k":[116],"v":[{"k":[97],"v":[{"k":[105],"v":[{"k":[108],"v":[{"k":[119],"v":[{"k":[105],"v":[{"k":[110],"v":[{"k":[100],"v":[{"k":[99],"v":[{"k":[115],"v":[{"k":[115],"v":[{"k":[46],"v":[{"k":[99],"v":[{"k":[111],"v":[{"k":[109],"v":[{"k":[47],"v":[{"k":[41],"v":[{"d":{"df":1,"dc":[[1,1]]}}]}]}]}]}]}]}]}]}]}]}]}]}]}]}]}]}]}]}]}]}]}]}]}]}]}]},{"d":{"df":1,"dc":[[5,1]]}}]}]},{"k":[114,115,109],"v":[{"k":[114],"v":[{"k":[101],"v":[{"k":[110],"v":[{"k":[116],"v":[{"d":{"df":1,"dc":[[1,1]]},"k":[108],"v":[{"k":[121],"v":[{"d":{"df":1,"dc":[[1,2]]}}]}]}]}]}]}]},{"k":[116],"v":[{"k":[111],"v":[{"k":[109],"v":[{"d":{"df":1,"dc":[[1,2]]},"k":[105],"v":[{"k":[122,115],"v":[{"k":[97],"v":[{"k":[116],"v":[{"k":[105],"v":[{"k":[111],"v":[{"k":[110],"v":[{"d":{"df":1,"dc":[[1,1]]}}]}]}]}]}]},{"k":[101],"v":[{"d":{"df":1,"dc":[[1,1]]}}]}]}]}]}]}]},{"k":[98],"v":[{"k":[101],"v":[{"k":[114],"v":[{"k":[115],"v":[{"k":[111],"v":[{"k":[109],"v":[{"k":[101],"v":[{"k":[46],"v":[{"d":{"df":1,"dc":[[4,1]]}}]}]}]}]}]}]}]}]}]},{"k":[109,112,110,117,108],"v":[{"k":[112,101,109],"v":[{"k":[111,108],"v":[{"k":[110],"v":[{"k":[101],"v":[{"k":[110],"v":[{"k":[116],"v":[{"d":{"df":1,"dc":[[1,3]]},"k":[46,115,58],"v":[{"d":{"df":1,"dc":[[1,1]]}},{"d":{"df":2,"dc":[[1,2],[4,1]]}},{"d":{"df":1,"dc":[[1,1]]}}]}]}]}]}]},{"k":[101],"v":[{"k":[116],"v":[{"k":[101],"v":[{"k":[108],"v":[{"k":[121],"v":[{"d":{"df":1,"dc":[[1,1]]}}]}]}]}]}]}]},{"k":[115],"v":[{"d":{"df":2,"dc":[[1,1],[5,2]]}}]},{"k":[105],"v":[{"k":[116],"v":[{"d":{"df":1,"dc":[[4,2]]},"k":[115],"v":[{"d":{"df":1,"dc":[[4,1]]}}]}]}]}]},{"k":[121],"v":[{"d":{"df":1,"dc":[[5,1]]},"k":[114],"v":[{"k":[105],"v":[{"k":[103],"v":[{"k":[104],"v":[{"k":[116],"v":[{"d":{"df":1,"dc":[[1,1]]}}]}]}]}]}]}]},{"k":[102,116,115],"v":[{"k":[105],"v":[{"k":[103],"v":[{"d":{"df":2,"dc":[[1,1],[4,2]]},"k":[117],"v":[{"k":[114],"v":[{"k":[97,101],"v":[{"k":[116],"v":[{"k":[105],"v":[{"k":[111],"v":[{"k":[110],"v":[{"d":{"df":1,"dc":[[4,2]]}}]}]}]}]},{"d":{"df":1,"dc":[[5,1]]}}]}]}]}]}]},{"k":[101],"v":[{"k":[110],"v":[{"k":[116],"v":[{"d":{"df":1,"dc":[[2,1]]},"k":[46,115],"v":[{"d":{"df":1,"dc":[[1,1]]}},{"d":{"df":1,"dc":[[5,1]]}}]}]}]}]},{"k":[116],"v":[{"k":[114],"v":[{"k":[97],"v":[{"k":[105],"v":[{"k":[110],"v":[{"d":{"df":1,"dc":[[4,1]]}}]}]}]}]}]}]},{"k":[108,110,114],"v":[{"k":[100],"v":[{"d":{"df":1,"dc":[[1,4]]}}]},{"k":[116],"v":[{"d":{"df":1,"dc":[[5,1]]}}]},{"k":[115],"v":[{"k":[101],"v":[{"k":[44],"v":[{"d":{"df":1,"dc":[[5,1]]}}]}]}]}]},{"k":[111],"v":[{"k":[114],"v":[{"d":{"df":1,"dc":[[2,1]]}}]}]}]},{"k":[97,105],"v":[{"k":[114,110],"v":[{"k":[116],"v":[{"k":[106],"v":[{"k":[115],"v":[{"d":{"df":1,"dc":[[1,1]]}}]}]}]},{"k":[103],"v":[{"k":[101,105],"v":[{"k":[115],"v":[{"d":{"df":1,"dc":[[4,1]]}}]},{"k":[110],"v":[{"k":[103],"v":[{"d":{"df":1,"dc":[[5,1]]}}]}]}]}]}]},{"k":[108],"v":[{"k":[100],"v":[{"d":{"df":1,"dc":[[1,1]]}}]}]}]},{"k":[58],"v":[{"d":{"df":1,"dc":[[4,1]]}}]},{"k":[101],"v":[{"k":[97],"v":[{"k":[116],"v":[{"k":[101],"v":[{"d":{"df":1,"dc":[[5,2]]}}]}]}]}]},{"k":[110],"v":[{"d":{"df":1,"dc":[[5,4]]}}]}]},{"k":[111,101,105,114,97,117],"v":[{"k":[110,114,111,108],"v":[{"k":[116],"v":[{"d":{"df":2,"dc":[[0,1],[2,1]]},"k":[45,115,44],"v":[{"k":[108],"v":[{"k":[105],"v":[{"k":[103],"v":[{"k":[104],"v":[{"k":[116],"v":[{"k":[39],"v":[{"k":[62],"v":[{"k":[116,60],"v":[{"k":[104],"v":[{"k":[111],"v":[{"k":[109],"v":[{"d":{"df":1,"dc":[[0,1]]}}]}]}]},{"k":[114],"v":[{"k":[111],"v":[{"k":[99],"v":[{"k":[107],"v":[{"k":[45],"v":[{"k":[98],"v":[{"k":[97],"v":[{"k":[110],"v":[{"k":[100],"v":[{"k":[45],"v":[{"k":[115],"v":[{"k":[105],"v":[{"k":[109],"v":[{"k":[112],"v":[{"k":[108],"v":[{"k":[101],"v":[{"k":[45],"v":[{"k":[105],"v":[{"k":[99],"v":[{"k":[111],"v":[{"k":[110],"v":[{"d":{"df":1,"dc":[[0,1]]}}]}]}]}]}]}]}]}]}]}]}]}]}]}]}]}]}]}]}]}]}]}]}]}]}]}]}]}]}]},{"d":{"df":1,"dc":[[0,1]]}},{"d":{"df":1,"dc":[[1,1]]}}]}]},{"d":{"df":3,"dc":[[1,2],[4,3],[5,2]]},"k":[109,119],"v":[{"k":[115],"v":[{"d":{"df":1,"dc":[[2,1]]},"k":[93],"v":[{"k":[40],"v":[{"k":[104],"v":[{"k":[116],"v":[{"k":[116],"v":[{"k":[112],"v":[{"k":[115],"v":[{"k":[58],"v":[{"k":[47],"v":[{"k":[47],"v":[{"k":[103],"v":[{"k":[105],"v":[{"k":[116],"v":[{"k":[104],"v":[{"k":[117],"v":[{"k":[98],"v":[{"k":[46],"v":[{"k":[99],"v":[{"k":[111],"v":[{"k":[109],"v":[{"k":[47],"v":[{"k":[116],"v":[{"k":[97],"v":[{"k":[105],"v":[{"k":[108],"v":[{"k":[119],"v":[{"k":[105],"v":[{"k":[110],"v":[{"k":[100],"v":[{"k":[108],"v":[{"k":[97],"v":[{"k":[98],"v":[{"k":[115],"v":[{"k":[47],"v":[{"k":[116],"v":[{"k":[97],"v":[{"k":[105],"v":[{"k":[108],"v":[{"k":[119],"v":[{"k":[105],"v":[{"k":[110],"v":[{"k":[100],"v":[{"k":[99],"v":[{"k":[115],"v":[{"k":[115],"v":[{"k":[45],"v":[{"k":[102],"v":[{"k":[111],"v":[{"k":[114],"v":[{"k":[109],"v":[{"k":[115],"v":[{"k":[41],"v":[{"d":{"df":1,"dc":[[1,1]]}}]}]}]}]}]}]}]}]}]}]}]}]}]}]}]}]}]}]}]}]}]}]}]}]}]}]}]}]}]}]}]}]}]}]}]}]}]}]}]}]}]}]}]}]}]}]}]}]}]}]}]}]}]},{"k":[97],"v":[{"k":[114],"v":[{"k":[100],"v":[{"k":[115],"v":[{"d":{"df":1,"dc":[[1,1]]}}]}]}]}]}]},{"k":[116],"v":[{"k":[101],"v":[{"k":[114],"v":[{"k":[59],"v":[{"d":{"df":1,"dc":[[1,1]]}}]}]}]}]},{"k":[108],"v":[{"k":[111],"v":[{"k":[119],"v":[{"k":[105],"v":[{"k":[110],"v":[{"k":[103],"v":[{"d":{"df":1,"dc":[[5,1]]}}]}]}]}]}]}]}]},{"k":[97,119],"v":[{"k":[116],"v":[{"k":[117],"v":[{"k":[114],"v":[{"k":[101],"v":[{"k":[115],"v":[{"d":{"df":1,"dc":[[1,2]]}}]}]}]}]}]},{"d":{"df":1,"dc":[[1,1]]}}]},{"k":[108],"v":[{"k":[101],"v":[{"d":{"df":3,"dc":[[1,1],[4,2],[5,2]]},"k":[46,115,44],"v":[{"d":{"df":1,"dc":[[4,1]]}},{"d":{"df":1,"dc":[[4,1]]}},{"d":{"df":2,"dc":[[4,1],[5,1]]}}]}]}]},{"k":[111],"v":[{"k":[109],"v":[{"d":{"df":2,"dc":[[1,1],[5,1]]}}]}]},{"k":[108],"v":[{"k":[108],"v":[{"k":[98],"v":[{"k":[97],"v":[{"k":[99],"v":[{"k":[107],"v":[{"d":{"df":1,"dc":[[4,1]]}}]}]}]}]}]}]},{"k":[116],"v":[{"k":[117],"v":[{"k":[114],"v":[{"k":[101],"v":[{"d":{"df":1,"dc":[[4,1]]}}]}]}]}]}]},{"k":[114,117,101,111,121,105],"v":[{"k":[117],"v":[{"k":[99],"v":[{"k":[101],"v":[{"k":[60],"v":[{"k":[47],"v":[{"k":[97],"v":[{"k":[62],"v":[{"d":{"df":1,"dc":[[0,1]]}}]}]}]}]}]}]}]},{"k":[105,116],"v":[{"k":[108],"v":[{"k":[116,100],"v":[{"d":{"df":1,"dc":[[0,1]]}},{"d":{"df":1,"dc":[[4,1]]},"k":[109],"v":[{"k":[111],"v":[{"k":[100],"v":[{"k":[117],"v":[{"k":[108],"v":[{"k":[101],"v":[{"k":[115],"v":[{"d":{"df":1,"dc":[[5,1]]},"k":[58],"v":[{"d":{"df":1,"dc":[[5,1]]}}]}]}]}]}]}]}]}]}]}]},{"d":{"df":2,"dc":[[1,1],[5,1]]}}]},{"d":{"df":1,"dc":[[1,5]]},"k":[116,105],"v":[{"k":[116],"v":[{"k":[101],"v":[{"k":[114],"v":[{"d":{"df":1,"dc":[[1,1]]}}]}]}]},{"k":[110],"v":[{"k":[103],"v":[{"k":[44],"v":[{"d":{"df":1,"dc":[[4,1]]}}]}]}]}]},{"k":[114,116],"v":[{"k":[114],"v":[{"k":[111],"v":[{"k":[119],"v":[{"d":{"df":1,"dc":[[1,1]]}}]}]}]},{"k":[104],"v":[{"d":{"df":1,"dc":[[5,1]]}}]}]},{"d":{"df":3,"dc":[[1,1],[4,1],[5,1]]}},{"k":[116],"v":[{"d":{"df":1,"dc":[[4,2]]}}]}]},{"d":{"df":2,"dc":[[1,4],[4,2]]},"k":[99,115,109,116,110,39,102,100],"v":[{"k":[111],"v":[{"k":[110],"v":[{"k":[61,115],"v":[{"k":[39],"v":[{"k":[110,116,102,115,103],"v":[{"k":[117],"v":[{"k":[120],"v":[{"k":[116],"v":[{"k":[100],"v":[{"k":[111],"v":[{"k":[116],"v":[{"k":[106],"v":[{"k":[115],"v":[{"k":[39],"v":[{"k":[62],"v":[{"k":[60],"v":[{"k":[47],"v":[{"k":[114],"v":[{"k":[111],"v":[{"k":[99],"v":[{"k":[107],"v":[{"k":[45],"v":[{"k":[98],"v":[{"k":[97],"v":[{"k":[110],"v":[{"k":[100],"v":[{"k":[45],"v":[{"k":[115],"v":[{"k":[105],"v":[{"k":[109],"v":[{"k":[112],"v":[{"k":[108],"v":[{"k":[101],"v":[{"k":[45],"v":[{"k":[105],"v":[{"k":[99],"v":[{"k":[111],"v":[{"k":[110],"v":[{"k":[62],"v":[{"d":{"df":1,"dc":[[0,1]]}}]}]}]}]}]}]}]}]}]}]}]}]}]}]}]}]}]}]}]}]}]}]}]}]}]}]}]}]}]}]}]}]}]}]},{"k":[97],"v":[{"k":[105],"v":[{"k":[108],"v":[{"k":[119],"v":[{"k":[105],"v":[{"k":[110],"v":[{"k":[100],"v":[{"k":[99],"v":[{"k":[115],"v":[{"k":[115],"v":[{"k":[39],"v":[{"k":[62],"v":[{"k":[60],"v":[{"k":[47],"v":[{"k":[114],"v":[{"k":[111],"v":[{"k":[99],"v":[{"k":[107],"v":[{"k":[45],"v":[{"k":[98],"v":[{"k":[97],"v":[{"k":[110],"v":[{"k":[100],"v":[{"k":[45],"v":[{"k":[115],"v":[{"k":[105],"v":[{"k":[109],"v":[{"k":[112],"v":[{"k":[108],"v":[{"k":[101],"v":[{"k":[45],"v":[{"k":[105],"v":[{"k":[99],"v":[{"k":[111],"v":[{"k":[110],"v":[{"k":[62],"v":[{"d":{"df":1,"dc":[[0,1]]}}]}]}]}]}]}]}]}]}]}]}]}]}]}]}]}]}]}]}]}]}]}]}]}]}]}]}]}]}]}]}]}]}]}]}]}]},{"k":[111],"v":[{"k":[110],"v":[{"k":[116],"v":[{"k":[97],"v":[{"k":[119],"v":[{"k":[101],"v":[{"k":[115],"v":[{"k":[111],"v":[{"k":[109],"v":[{"k":[101],"v":[{"k":[39],"v":[{"k":[62],"v":[{"k":[60],"v":[{"k":[47],"v":[{"k":[114],"v":[{"k":[111],"v":[{"k":[99],"v":[{"k":[107],"v":[{"k":[45],"v":[{"k":[98],"v":[{"k":[97],"v":[{"k":[110],"v":[{"k":[100],"v":[{"k":[45],"v":[{"k":[115],"v":[{"k":[105],"v":[{"k":[109],"v":[{"k":[112],"v":[{"k":[108],"v":[{"k":[101],"v":[{"k":[45],"v":[{"k":[105],"v":[{"k":[99],"v":[{"k":[111],"v":[{"k":[110],"v":[{"k":[62],"v":[{"d":{"df":1,"dc":[[0,1]]}}]}]}]}]}]}]}]}]}]}]}]}]}]}]}]}]}]}]}]}]}]}]}]}]}]}]}]}]}]}]}]}]}]}]}]}]},{"k":[105],"v":[{"k":[109],"v":[{"k":[112],"v":[{"k":[108],"v":[{"k":[101],"v":[{"k":[105],"v":[{"k":[99],"v":[{"k":[111],"v":[{"k":[110],"v":[{"k":[115],"v":[{"k":[39],"v":[{"k":[62],"v":[{"k":[60],"v":[{"k":[47],"v":[{"k":[114],"v":[{"k":[111],"v":[{"k":[99],"v":[{"k":[107],"v":[{"k":[45],"v":[{"k":[98],"v":[{"k":[97],"v":[{"k":[110],"v":[{"k":[100],"v":[{"k":[45],"v":[{"k":[115],"v":[{"k":[105],"v":[{"k":[109],"v":[{"k":[112],"v":[{"k":[108],"v":[{"k":[101],"v":[{"k":[45],"v":[{"k":[105],"v":[{"k":[99],"v":[{"k":[111],"v":[{"k":[110],"v":[{"k":[62],"v":[{"d":{"df":1,"dc":[[0,1]]}}]}]}]}]}]}]}]}]}]}]}]}]}]}]}]}]}]}]}]}]}]}]}]}]}]}]}]}]}]}]}]}]}]}]}]}]},{"k":[105],"v":[{"k":[116],"v":[{"k":[104],"v":[{"k":[117],"v":[{"k":[98],"v":[{"k":[39],"v":[{"k":[62],"v":[{"k":[60],"v":[{"k":[47],"v":[{"k":[114],"v":[{"k":[111],"v":[{"k":[99],"v":[{"k":[107],"v":[{"k":[45],"v":[{"k":[98],"v":[{"k":[97],"v":[{"k":[110],"v":[{"k":[100],"v":[{"k":[45],"v":[{"k":[115],"v":[{"k":[105],"v":[{"k":[109],"v":[{"k":[112],"v":[{"k":[108],"v":[{"k":[101],"v":[{"k":[45],"v":[{"k":[105],"v":[{"k":[99],"v":[{"k":[111],"v":[{"k":[110],"v":[{"k":[62],"v":[{"d":{"df":1,"dc":[[0,1]]}}]}]}]}]}]}]}]}]}]}]}]}]}]}]}]}]}]}]}]}]}]}]}]}]}]}]}]}]}]}]}]}]}]},{"d":{"df":1,"dc":[[2,1]]},"k":[60,93],"v":[{"k":[47],"v":[{"k":[97],"v":[{"k":[62],"v":[{"d":{"df":1,"dc":[[0,1]]}}]}]}]},{"k":[40],"v":[{"k":[104],"v":[{"k":[116],"v":[{"k":[116],"v":[{"k":[112],"v":[{"k":[115],"v":[{"k":[58],"v":[{"k":[47],"v":[{"k":[47],"v":[{"k":[115],"v":[{"k":[105],"v":[{"k":[109],"v":[{"k":[112],"v":[{"k":[108],"v":[{"k":[101],"v":[{"k":[105],"v":[{"k":[99],"v":[{"k":[111],"v":[{"k":[110],"v":[{"k":[115],"v":[{"k":[46],"v":[{"k":[111],"v":[{"k":[114],"v":[{"k":[103],"v":[{"k":[47],"v":[{"k":[41],"v":[{"d":{"df":1,"dc":[[1,1]]}}]}]}]}]}]}]}]}]}]}]}]}]}]}]}]}]}]}]}]}]}]}]}]}]}]}]}]}]}]}]},{"d":{"df":3,"dc":[[1,6],[4,1],[5,2]]},"k":[110],"v":[{"k":[39],"v":[{"k":[116],"v":[{"d":{"df":1,"dc":[[1,1]]}}]}]}]},{"k":[97,112],"v":[{"k":[103],"v":[{"k":[101],"v":[{"d":{"df":2,"dc":[[2,1],[4,1]]},"k":[93,44],"v":[{"k":[40],"v":[{"k":[104],"v":[{"k":[116],"v":[{"k":[116],"v":[{"k":[112],"v":[{"k":[115],"v":[{"k":[58],"v":[{"k":[47],"v":[{"k":[47],"v":[{"k":[105],"v":[{"k":[109],"v":[{"k":[97],"v":[{"k":[103],"v":[{"k":[101],"v":[{"k":[46],"v":[{"k":[110],"v":[{"k":[117],"v":[{"k":[120],"v":[{"k":[116],"v":[{"k":[106],"v":[{"k":[115],"v":[{"k":[46],"v":[{"k":[111],"v":[{"k":[114],"v":[{"k":[103],"v":[{"k":[47],"v":[{"k":[41],"v":[{"d":{"df":1,"dc":[[1,1]]}}]}]}]}]}]}]}]}]}]}]}]}]}]}]}]}]}]}]}]}]}]}]}]}]}]}]}]},{"d":{"df":1,"dc":[[1,1]]}}]}]}]},{"k":[111],"v":[{"k":[114],"v":[{"k":[116],"v":[{"d":{"df":1,"dc":[[5,1]]},"k":[115],"v":[{"d":{"df":1,"dc":[[5,1]]},"k":[46],"v":[{"d":{"df":1,"dc":[[5,1]]}}]}]}]}]}]}]},{"d":{"df":2,"dc":[[1,3],[4,3]]},"k":[44,115,39],"v":[{"d":{"df":1,"dc":[[1,1]]}},{"d":{"df":1,"dc":[[5,1]]},"k":[101],"v":[{"k":[108],"v":[{"k":[102],"v":[{"d":{"df":1,"dc":[[4,1]]}}]}]}]},{"k":[115],"v":[{"d":{"df":1,"dc":[[5,1]]}}]}]},{"d":{"df":3,"dc":[[1,5],[4,3],[5,2]]},"k":[116,99,106,115,105],"v":[{"k":[111,101],"v":[{"d":{"df":1,"dc":[[1,2]]}},{"k":[103],"v":[{"k":[114],"v":[{"k":[97],"v":[{"k":[116],"v":[{"k":[105],"v":[{"k":[110,111],"v":[{"k":[103],"v":[{"d":{"df":1,"dc":[[1,1]]}}]},{"k":[110],"v":[{"d":{"df":1,"dc":[[1,1]]}}]}]}]}]}]}]}]}]},{"k":[108],"v":[{"k":[117],"v":[{"k":[100],"v":[{"k":[101],"v":[{"d":{"df":1,"dc":[[1,1]]}}]}]}]}]},{"k":[101],"v":[{"k":[99],"v":[{"k":[116],"v":[{"d":{"df":1,"dc":[[1,1]]}}]}]}]},{"k":[116],"v":[{"k":[97],"v":[{"k":[108,110],"v":[{"k":[108],"v":[{"k":[97],"v":[{"k":[116],"v":[{"k":[105],"v":[{"k":[111],"v":[{"k":[110],"v":[{"d":{"df":2,"dc":[[4,2],[5,1]]},"k":[46],"v":[{"d":{"df":1,"dc":[[5,1]]}}]}]}]}]}]}]}]},{"k":[99],"v":[{"k":[101],"v":[{"d":{"df":1,"dc":[[5,1]]}}]}]}]}]}]},{"k":[116],"v":[{"k":[105],"v":[{"k":[97],"v":[{"k":[108],"v":[{"k":[105],"v":[{"k":[122],"v":[{"k":[101],"v":[{"k":[114],"v":[{"k":[58],"v":[{"d":{"df":1,"dc":[[5,1]]}}]}]}]}]}]}]}]}]}]}]},{"k":[100,118],"v":[{"d":{"df":1,"dc":[[1,1]]}},{"k":[101],"v":[{"d":{"df":1,"dc":[[4,1]]}}]}]},{"d":{"df":1,"dc":[[1,1]]}},{"k":[101],"v":[{"k":[97],"v":[{"k":[108],"v":[{"d":{"df":1,"dc":[[4,1]]}}]}]}]}]},{"k":[117,111,101,97],"v":[{"k":[120,109],"v":[{"k":[116],"v":[{"d":{"df":3,"dc":[[1,6],[2,5],[5,1]]},"k":[46,39],"v":[{"d":{"df":2,"dc":[[4,1],[5,1]]},"k":[106],"v":[{"k":[115],"v":[{"k":[60],"v":[{"k":[47],"v":[{"k":[97],"v":[{"k":[62],"v":[{"d":{"df":1,"dc":[[0,1]]}}]}]}]}]}]}]},{"k":[115],"v":[{"d":{"df":1,"dc":[[4,1]]}}]}]}]},{"k":[101],"v":[{"k":[114],"v":[{"k":[111],"v":[{"k":[117],"v":[{"k":[115],"v":[{"d":{"df":1,"dc":[[4,1]]}}]}]}]}]}]}]},{"d":{"df":1,"dc":[[1,1]]},"k":[116],"v":[{"d":{"df":1,"dc":[[1,2]]},"k":[105],"v":[{"k":[99],"v":[{"k":[101],"v":[{"k":[44],"v":[{"d":{"df":1,"dc":[[1,1]]}}]}]}]}]}]},{"k":[115,101,119,99],"v":[{"k":[116],"v":[{"k":[101],"v":[{"k":[100],"v":[{"d":{"df":1,"dc":[[1,2]]},"k":[44],"v":[{"d":{"df":1,"dc":[[1,1]]}}]}]}]}]},{"k":[100],"v":[{"d":{"df":2,"dc":[[1,1],[5,1]]}}]},{"d":{"df":1,"dc":[[4,1]]}},{"k":[101],"v":[{"k":[115],"v":[{"k":[115],"v":[{"k":[97],"v":[{"k":[114],"v":[{"k":[121],"v":[{"d":{"df":1,"dc":[[5,1]]}}]}]}]}]}]}]}]},{"k":[109],"v":[{"k":[101],"v":[{"k":[115],"v":[{"d":{"df":1,"dc":[[5,1]]}}]}]}]}]},{"k":[100,101,105,121,97,111],"v":[{"k":[58],"v":[{"k":[104,105],"v":[{"k":[105],"v":[{"k":[100],"v":[{"k":[100],"v":[{"k":[101],"v":[{"k":[110],"v":[{"k":[39],"v":[{"k":[47],"v":[{"k":[62],"v":[{"k":[60],"v":[{"k":[115],"v":[{"k":[112],"v":[{"k":[97],"v":[{"k":[110],"v":[{"d":{"df":1,"dc":[[0,2]]}}]}]}]}]}]}]}]}]}]}]}]}]}]},{"k":[110],"v":[{"k":[108],"v":[{"k":[105],"v":[{"k":[110],"v":[{"k":[101],"v":[{"k":[39],"v":[{"k":[62],"v":[{"k":[38],"v":[{"k":[101],"v":[{"k":[109],"v":[{"k":[115],"v":[{"k":[112],"v":[{"k":[59],"v":[{"k":[60],"v":[{"k":[47],"v":[{"k":[115],"v":[{"k":[112],"v":[{"k":[97],"v":[{"k":[110],"v":[{"k":[62],"v":[{"d":{"df":1,"dc":[[0,2]]}}]}]}]}]}]}]}]}]}]}]}]}]}]}]}]}]}]}]}]}]}]}]},{"k":[110,97,116,114],"v":[{"k":[117],"v":[{"d":{"df":1,"dc":[[1,1]]},"k":[115,46],"v":[{"d":{"df":1,"dc":[[1,1]]}},{"d":{"df":1,"dc":[[1,1]]}}]}]},{"k":[110],"v":[{"k":[116],"v":[{"k":[105],"v":[{"k":[109],"v":[{"k":[101],"v":[{"k":[44],"v":[{"d":{"df":1,"dc":[[1,1]]}}]}]}]}]}]}]},{"k":[97],"v":[{"d":{"df":1,"dc":[[2,1]]}}]},{"k":[103],"v":[{"k":[101],"v":[{"d":{"df":1,"dc":[[4,1]]}}]}]}]},{"k":[103],"v":[{"k":[104],"v":[{"k":[116],"v":[{"d":{"df":1,"dc":[[1,1]]}}]}]}]},{"d":{"df":1,"dc":[[1,1]]}},{"k":[107,121,110],"v":[{"k":[101],"v":[{"d":{"df":1,"dc":[[1,3]]},"k":[115],"v":[{"d":{"df":2,"dc":[[1,1],[4,1]]}}]}]},{"d":{"df":1,"dc":[[1,1]]}},{"k":[117],"v":[{"k":[97],"v":[{"k":[108],"v":[{"k":[108],"v":[{"k":[121],"v":[{"d":{"df":1,"dc":[[4,1]]}}]}]}]}]}]}]},{"k":[118,114,100],"v":[{"k":[101],"v":[{"k":[100],"v":[{"d":{"df":1,"dc":[[1,1]]}}]}]},{"k":[101],"v":[{"d":{"df":1,"dc":[[1,1]]},"k":[46],"v":[{"d":{"df":1,"dc":[[4,1]]}}]}]},{"k":[101,105,117],"v":[{"d":{"df":1,"dc":[[2,1]]}},{"k":[102],"v":[{"k":[105,121],"v":[{"k":[99],"v":[{"k":[97],"v":[{"k":[116],"v":[{"k":[105],"v":[{"k":[111],"v":[{"k":[110],"v":[{"k":[115],"v":[{"d":{"df":1,"dc":[[4,1]]}}]}]}]}]}]}]}]},{"k":[105],"v":[{"k":[110],"v":[{"k":[103],"v":[{"d":{"df":1,"dc":[[5,1]]}}]}]}]}]}]},{"k":[108],"v":[{"k":[101],"v":[{"d":{"df":1,"dc":[[4,1]]}}]}]}]}]}]},{"k":[97,104,111,114,105,101,121,119],"v":[{"k":[105,120],"v":[{"k":[108],"v":[{"k":[119],"v":[{"k":[105],"v":[{"k":[110],"v":[{"k":[100],"v":[{"d":{"df":4,"dc":[[0,1],[2,1],[4,1],[5,2]]}}]}]}]}]}]},{"k":[111],"v":[{"k":[110],"v":[{"k":[111],"v":[{"k":[109],"v":[{"k":[105],"v":[{"k":[101],"v":[{"k":[115],"v":[{"d":{"df":1,"dc":[[2,1]]},"k":[93],"v":[{"k":[40],"v":[{"k":[104],"v":[{"k":[116],"v":[{"k":[116],"v":[{"k":[112],"v":[{"k":[115],"v":[{"k":[58],"v":[{"k":[47],"v":[{"k":[47],"v":[{"k":[103],"v":[{"k":[105],"v":[{"k":[116],"v":[{"k":[104],"v":[{"k":[117],"v":[{"k":[98],"v":[{"k":[46],"v":[{"k":[99],"v":[{"k":[111],"v":[{"k":[109],"v":[{"k":[47],"v":[{"k":[116],"v":[{"k":[104],"v":[{"k":[111],"v":[{"k":[109],"v":[{"k":[98],"v":[{"k":[114],"v":[{"k":[117],"v":[{"k":[99],"v":[{"k":[101],"v":[{"k":[47],"v":[{"k":[110],"v":[{"k":[117],"v":[{"k":[120],"v":[{"k":[116],"v":[{"k":[45],"v":[{"k":[116],"v":[{"k":[97],"v":[{"k":[120],"v":[{"k":[111],"v":[{"k":[110],"v":[{"k":[111],"v":[{"k":[109],"v":[{"k":[105],"v":[{"k":[101],"v":[{"k":[115],"v":[{"k":[41],"v":[{"d":{"df":1,"dc":[[1,1]]}}]}]}]}]}]}]}]}]}]}]}]}]}]}]}]}]}]}]}]}]}]}]}]}]}]}]}]}]}]}]}]}]}]}]}]}]}]}]}]}]}]}]}]}]}]}]}]}]}]}]}]}]}]}]}]},{"k":[97,101,111,105,114],"v":[{"k":[116],"v":[{"d":{"df":2,"dc":[[1,3],[4,1]]}}]},{"d":{"df":3,"dc":[[1,11],[4,12],[5,3]]},"k":[115,114,121,105,109],"v":[{"k":[101],"v":[{"d":{"df":2,"dc":[[1,3],[5,1]]}}]},{"k":[101],"v":[{"d":{"df":1,"dc":[[1,1]]}}]},{"d":{"df":1,"dc":[[1,1]]}},{"k":[114],"v":[{"d":{"df":1,"dc":[[5,2]]}}]},{"d":{"df":1,"dc":[[5,1]]}}]},{"k":[117],"v":[{"k":[103],"v":[{"k":[104],"v":[{"k":[44],"v":[{"d":{"df":1,"dc":[[1,1]]}}]}]}]}]},{"k":[115],"v":[{"d":{"df":3,"dc":[[1,4],[4,1],[5,3]]}}]},{"k":[101],"v":[{"k":[101],"v":[{"d":{"df":1,"dc":[[4,1]]}}]}]}]},{"d":{"df":3,"dc":[[1,12],[4,8],[5,7]]},"k":[100],"v":[{"k":[111],"v":[{"d":{"df":2,"dc":[[3,1],[4,1]]}}]}]},{"k":[117],"v":[{"k":[101],"v":[{"d":{"df":1,"dc":[[1,1]]}}]}]},{"k":[116,109],"v":[{"k":[108],"v":[{"k":[101],"v":[{"d":{"df":1,"dc":[[1,1]]}}]}]},{"k":[101],"v":[{"d":{"df":1,"dc":[[4,1]]}}]}]},{"k":[109],"v":[{"k":[112],"v":[{"k":[108],"v":[{"k":[97],"v":[{"k":[116],"v":[{"k":[101],"v":[{"k":[115],"v":[{"d":{"df":1,"dc":[[1,2]]},"k":[44],"v":[{"d":{"df":1,"dc":[[4,1]]}}]}]}]}]}]}]}]}]},{"k":[112],"v":[{"k":[111],"v":[{"k":[103],"v":[{"k":[114],"v":[{"k":[97],"v":[{"k":[112],"v":[{"k":[104],"v":[{"k":[121],"v":[{"d":{"df":1,"dc":[[2,1]]}}]}]}]}]}]}]}]}]},{"k":[111],"v":[{"d":{"df":1,"dc":[[4,1]]},"k":[58],"v":[{"d":{"df":1,"dc":[[4,1]]}}]}]}]},{"d":{"df":3,"dc":[[1,11],[4,5],[5,3]]},"k":[119,116,110,117,108,115,114,112,100],"v":[{"k":[101,97],"v":[{"k":[115],"v":[{"k":[111],"v":[{"k":[109],"v":[{"k":[101],"v":[{"d":{"df":1,"dc":[[2,1]]},"k":[60,93],"v":[{"k":[47],"v":[{"k":[97],"v":[{"k":[62],"v":[{"d":{"df":1,"dc":[[0,1]]}}]}]}]},{"k":[40],"v":[{"k":[104],"v":[{"k":[116],"v":[{"k":[116],"v":[{"k":[112],"v":[{"k":[115],"v":[{"k":[58],"v":[{"k":[47],"v":[{"k":[47],"v":[{"k":[102],"v":[{"k":[111],"v":[{"k":[110],"v":[{"k":[116],"v":[{"k":[97],"v":[{"k":[119],"v":[{"k":[101],"v":[{"k":[115],"v":[{"k":[111],"v":[{"k":[109],"v":[{"k":[101],"v":[{"k":[46],"v":[{"k":[99],"v":[{"k":[111],"v":[{"k":[109],"v":[{"k":[47],"v":[{"k":[41],"v":[{"d":{"df":1,"dc":[[1,1]]}}]}]}]}]}]}]}]}]}]}]}]}]}]}]}]}]}]}]}]}]}]}]}]}]}]}]}]}]}]}]}]},{"k":[114],"v":[{"k":[101],"v":[{"d":{"df":1,"dc":[[1,1]]}}]}]}]},{"d":{"df":2,"dc":[[1,2],[5,2]]}},{"d":{"df":1,"dc":[[1,2]]},"k":[100,111,121],"v":[{"d":{"df":3,"dc":[[1,4],[4,8],[5,6]]}},{"k":[116],"v":[{"k":[104],"v":[{"k":[101],"v":[{"k":[114],"v":[{"d":{"df":1,"dc":[[1,1]]}}]}]}]}]},{"d":{"df":1,"dc":[[5,2]]},"k":[109],"v":[{"k":[111],"v":[{"k":[114],"v":[{"k":[101],"v":[{"k":[44],"v":[{"d":{"df":1,"dc":[[1,1]]}}]}]}]}]}]}]},{"k":[116],"v":[{"k":[111],"v":[{"k":[109,112],"v":[{"k":[97],"v":[{"k":[116],"v":[{"k":[105],"v":[{"k":[99],"v":[{"d":{"df":1,"dc":[[1,2]]}}]}]}]}]},{"k":[114],"v":[{"k":[101],"v":[{"k":[102],"v":[{"k":[105],"v":[{"k":[120],"v":[{"k":[101],"v":[{"k":[114],"v":[{"d":{"df":1,"dc":[[2,1]]}}]}]}]}]}]}]}]}]}]}]},{"k":[115,108],"v":[{"k":[111],"v":[{"d":{"df":3,"dc":[[1,2],[4,2],[5,1]]}}]},{"d":{"df":1,"dc":[[1,1]]}}]},{"d":{"df":3,"dc":[[1,1],[4,1],[5,1]]}},{"k":[101],"v":[{"d":{"df":1,"dc":[[1,1]]}}]},{"k":[112,105,97],"v":[{"d":{"df":1,"dc":[[1,1]]},"k":[115],"v":[{"d":{"df":1,"dc":[[1,1]]}}]},{"k":[93],"v":[{"k":[40],"v":[{"k":[104],"v":[{"k":[116],"v":[{"k":[116],"v":[{"k":[112],"v":[{"k":[115],"v":[{"k":[58],"v":[{"k":[47],"v":[{"k":[47],"v":[{"k":[103],"v":[{"k":[105],"v":[{"k":[116],"v":[{"k":[104],"v":[{"k":[117],"v":[{"k":[98],"v":[{"k":[46],"v":[{"k":[99],"v":[{"k":[111],"v":[{"k":[109],"v":[{"k":[47],"v":[{"k":[110],"v":[{"k":[117],"v":[{"k":[120],"v":[{"k":[116],"v":[{"k":[47],"v":[{"k":[114],"v":[{"k":[102],"v":[{"k":[99],"v":[{"k":[115],"v":[{"k":[47],"v":[{"k":[105],"v":[{"k":[115],"v":[{"k":[115],"v":[{"k":[117],"v":[{"k":[101],"v":[{"k":[115],"v":[{"k":[47],"v":[{"k":[51],"v":[{"k":[48],"v":[{"k":[41],"v":[{"d":{"df":1,"dc":[[1,1]]}}]}]}]}]}]}]}]}]}]}]}]}]}]}]}]}]}]}]}]}]}]}]}]}]}]}]}]}]}]}]}]}]}]}]}]}]}]}]}]}]}]},{"k":[114],"v":[{"k":[116],"v":[{"d":{"df":1,"dc":[[5,1]]}}]}]}]},{"k":[100],"v":[{"d":{"df":3,"dc":[[1,1],[4,2],[5,6]]},"k":[115],"v":[{"d":{"df":1,"dc":[[4,2]]}}]}]}]},{"k":[105,111,101,104,116,117],"v":[{"k":[109,122,110,116],"v":[{"k":[112],"v":[{"k":[108],"v":[{"k":[101],"v":[{"d":{"df":2,"dc":[[0,1],[2,1]]}}]}]}]},{"k":[101],"v":[{"k":[44],"v":[{"d":{"df":1,"dc":[[1,1]]}}]}]},{"k":[103],"v":[{"k":[108],"v":[{"k":[101],"v":[{"d":{"df":1,"dc":[[4,1]]}}]}]}]},{"k":[101],"v":[{"d":{"df":1,"dc":[[4,1]]}}]}]},{"k":[99,109,108],"v":[{"k":[105],"v":[{"k":[97],"v":[{"k":[108],"v":[{"d":{"df":1,"dc":[[1,1]]}}]}]}]},{"k":[101],"v":[{"d":{"df":1,"dc":[[1,1]]}}]},{"k":[117],"v":[{"k":[116],"v":[{"k":[105],"v":[{"k":[111],"v":[{"k":[110],"v":[{"d":{"df":1,"dc":[[1,3]]}}]}]}]}]}]}]},{"k":[114,110,112,116],"v":[{"k":[118],"v":[{"k":[101],"v":[{"k":[100],"v":[{"d":{"df":1,"dc":[[1,1]]}}]}]}]},{"k":[115],"v":[{"k":[101],"v":[{"k":[44],"v":[{"d":{"df":1,"dc":[[1,2]]}}]}]}]},{"k":[97],"v":[{"k":[114],"v":[{"k":[97],"v":[{"k":[116],"v":[{"k":[101],"v":[{"k":[108],"v":[{"k":[121],"v":[{"k":[41],"v":[{"k":[95],"v":[{"d":{"df":1,"dc":[[2,1]]}}]}]}]}]}]}]}]}]}]},{"k":[117],"v":[{"k":[112],"v":[{"d":{"df":1,"dc":[[5,1]]}}]}]}]},{"k":[111],"v":[{"k":[117],"v":[{"k":[108],"v":[{"k":[100],"v":[{"d":{"df":1,"dc":[[1,1]]}}]}]}]}]},{"k":[114,97,105,121],"v":[{"k":[117],"v":[{"k":[99],"v":[{"k":[116],"v":[{"k":[117],"v":[{"k":[114],"v":[{"k":[97],"v":[{"k":[108],"v":[{"d":{"df":1,"dc":[[1,1]]}}]}]}]}]}]}]}]},{"k":[116],"v":[{"k":[105],"v":[{"k":[99],"v":[{"d":{"df":1,"dc":[[4,1]]}}]}]}]},{"k":[108],"v":[{"k":[108],"v":[{"d":{"df":1,"dc":[[5,1]]}}]}]},{"k":[108],"v":[{"k":[101],"v":[{"k":[115],"v":[{"d":{"df":1,"dc":[[5,2]]}}]}]}]}]},{"k":[112],"v":[{"k":[112],"v":[{"k":[111],"v":[{"k":[114],"v":[{"k":[116],"v":[{"d":{"df":1,"dc":[[1,1]]}}]}]}]}]}]}]},{"k":[105,111,101],"v":[{"k":[116],"v":[{"k":[104],"v":[{"k":[117],"v":[{"k":[98],"v":[{"k":[60,39],"v":[{"k":[47],"v":[{"k":[97],"v":[{"k":[62],"v":[{"d":{"df":1,"dc":[[0,1]]}}]}]}]},{"k":[115],"v":[{"d":{"df":1,"dc":[[4,1]]}}]}]}]}]}]}]},{"d":{"df":1,"dc":[[1,1]]},"k":[111],"v":[{"k":[100],"v":[{"d":{"df":1,"dc":[[5,1]]}}]}]},{"k":[110],"v":[{"k":[101],"v":[{"k":[114],"v":[{"k":[97],"v":[{"k":[116],"v":[{"k":[101],"v":[{"k":[100],"v":[{"d":{"df":1,"dc":[[4,1]]}}]}]}]}]}]}]}]}]},{"k":[111,101,117],"v":[{"k":[99],"v":[{"k":[107],"v":[{"k":[98],"v":[{"k":[97],"v":[{"k":[110],"v":[{"k":[100],"v":[{"d":{"df":3,"dc":[[1,6],[4,1],[5,5]]},"k":[46],"v":[{"d":{"df":1,"dc":[[4,1]]}}]}]}]}]}]}]}]},{"k":[102,109],"v":[{"k":[101],"v":[{"k":[114],"v":[{"k":[101],"v":[{"k":[110],"v":[{"k":[99],"v":[{"k":[101],"v":[{"d":{"df":1,"dc":[[4,1]]},"k":[115],"v":[{"d":{"df":1,"dc":[[4,1]]}}]}]}]}]}]}]}]},{"k":[111],"v":[{"k":[118],"v":[{"k":[101],"v":[{"k":[115],"v":[{"d":{"df":1,"dc":[[4,1]]}}]}]}]}]}]},{"k":[110],"v":[{"d":{"df":1,"dc":[[5,1]]},"k":[115],"v":[{"d":{"df":1,"dc":[[4,1]]}}]}]}]},{"k":[105,111,97,117],"v":[{"k":[98,107,115,110],"v":[{"k":[114],"v":[{"k":[97],"v":[{"k":[114],"v":[{"k":[121],"v":[{"d":{"df":1,"dc":[[1,1]]}}]}]}]}]},{"k":[101],"v":[{"d":{"df":3,"dc":[[1,1],[4,1],[5,1]]}}]},{"k":[116],"v":[{"d":{"df":1,"dc":[[1,1]]}}]},{"k":[107],"v":[{"k":[115],"v":[{"d":{"df":1,"dc":[[1,1]]}}]}]}]},{"k":[103,111,100,99],"v":[{"k":[105],"v":[{"k":[99],"v":[{"d":{"df":1,"dc":[[1,1]]}}]}]},{"k":[107],"v":[{"d":{"df":1,"dc":[[5,1]]},"k":[105],"v":[{"k":[110],"v":[{"k":[103],"v":[{"d":{"df":1,"dc":[[1,1]]}}]}]}]}]},{"k":[97],"v":[{"k":[115],"v":[{"k":[104],"v":[{"d":{"df":1,"dc":[[2,1]]}}]}]}]},{"k":[97],"v":[{"k":[108],"v":[{"d":{"df":1,"dc":[[5,1]]}}]}]}]},{"k":[121],"v":[{"k":[111],"v":[{"k":[117],"v":[{"k":[116],"v":[{"d":{"df":1,"dc":[[1,1]]},"k":[44],"v":[{"d":{"df":1,"dc":[[5,1]]}}]}]}]}]}]},{"k":[120],"v":[{"k":[111],"v":[{"k":[110],"v":[{"d":{"df":1,"dc":[[2,1]]}}]}]}]}]},{"d":{"df":3,"dc":[[1,11],[2,14],[5,1]]},"k":[45],"v":[{"k":[100],"v":[{"k":[101],"v":[{"k":[118],"v":[{"d":{"df":1,"dc":[[5,2]]},"k":[96],"v":[{"d":{"df":1,"dc":[[4,1]]}}]}]}]}]}]},{"d":{"df":1,"dc":[[5,1]]},"k":[110,112,116,102,115,108],"v":[{"k":[117],"v":[{"k":[120],"v":[{"k":[116],"v":[{"d":{"df":1,"dc":[[1,2]]},"k":[45],"v":[{"k":[101],"v":[{"k":[120],"v":[{"k":[116],"v":[{"k":[101],"v":[{"k":[110],"v":[{"k":[100],"v":[{"k":[93],"v":[{"k":[40],"v":[{"k":[104],"v":[{"k":[116],"v":[{"k":[116],"v":[{"k":[112],"v":[{"k":[115],"v":[{"k":[58],"v":[{"k":[47],"v":[{"k":[47],"v":[{"k":[103],"v":[{"k":[105],"v":[{"k":[116],"v":[{"k":[104],"v":[{"k":[117],"v":[{"k":[98],"v":[{"k":[46],"v":[{"k":[99],"v":[{"k":[111],"v":[{"k":[109],"v":[{"k":[47],"v":[{"k":[110],"v":[{"k":[117],"v":[{"k":[120],"v":[{"k":[116],"v":[{"k":[45],"v":[{"k":[99],"v":[{"k":[111],"v":[{"k":[109],"v":[{"k":[109],"v":[{"k":[117],"v":[{"k":[110],"v":[{"k":[105],"v":[{"k":[116],"v":[{"k":[121],"v":[{"k":[47],"v":[{"k":[110],"v":[{"k":[117],"v":[{"k":[120],"v":[{"k":[116],"v":[{"k":[45],"v":[{"k":[101],"v":[{"k":[120],"v":[{"k":[116],"v":[{"k":[101],"v":[{"k":[110],"v":[{"k":[100],"v":[{"k":[41],"v":[{"k":[59],"v":[{"d":{"df":1,"dc":[[1,1]]}}]}]}]}]}]}]}]}]}]}]}]}]}]}]}]}]}]}]}]}]}]}]}]}]}]}]}]}]}]}]}]}]}]}]}]}]}]}]}]}]}]}]}]}]}]}]}]}]}]}]}]}]}]}]}]}]}]}]}]},{"k":[117,111,108],"v":[{"k":[103],"v":[{"k":[93],"v":[{"k":[40],"v":[{"k":[104],"v":[{"k":[116],"v":[{"k":[116],"v":[{"k":[112],"v":[{"k":[115],"v":[{"k":[58],"v":[{"k":[47],"v":[{"k":[47],"v":[{"k":[112],"v":[{"k":[117],"v":[{"k":[103],"v":[{"k":[106],"v":[{"k":[115],"v":[{"k":[46],"v":[{"k":[111],"v":[{"k":[114],"v":[{"k":[103],"v":[{"k":[47],"v":[{"k":[97],"v":[{"k":[112],"v":[{"k":[105],"v":[{"k":[47],"v":[{"k":[103],"v":[{"k":[101],"v":[{"k":[116],"v":[{"k":[116],"v":[{"k":[105],"v":[{"k":[110],"v":[{"k":[103],"v":[{"k":[45],"v":[{"k":[115],"v":[{"k":[116],"v":[{"k":[97],"v":[{"k":[114],"v":[{"k":[116],"v":[{"k":[101],"v":[{"k":[100],"v":[{"k":[46],"v":[{"k":[104],"v":[{"k":[116],"v":[{"k":[109],"v":[{"k":[108],"v":[{"k":[41],"v":[{"d":{"df":1,"dc":[[1,1]]}}]}]}]}]}]}]}]}]}]}]}]}]}]}]}]}]}]}]}]}]}]}]}]}]}]}]}]}]}]}]}]}]}]}]}]}]}]}]}]}]}]}]}]}]}]}]},{"k":[115,114],"v":[{"k":[116],"v":[{"k":[99],"v":[{"k":[115],"v":[{"k":[115],"v":[{"k":[93],"v":[{"k":[40],"v":[{"k":[104],"v":[{"k":[116],"v":[{"k":[116],"v":[{"k":[112],"v":[{"k":[115],"v":[{"k":[58],"v":[{"k":[47],"v":[{"k":[47],"v":[{"k":[112],"v":[{"k":[111],"v":[{"k":[115],"v":[{"k":[116],"v":[{"k":[99],"v":[{"k":[115],"v":[{"k":[115],"v":[{"k":[46],"v":[{"k":[111],"v":[{"k":[114],"v":[{"k":[103],"v":[{"k":[47],"v":[{"k":[41],"v":[{"d":{"df":1,"dc":[[1,1]]}}]}]}]}]}]}]}]}]}]}]}]}]}]}]}]}]}]}]}]}]}]}]}]}]}]}]}]},{"k":[116],"v":[{"k":[97],"v":[{"k":[108],"v":[{"k":[118],"v":[{"k":[117],"v":[{"k":[101],"v":[{"k":[93],"v":[{"k":[40],"v":[{"k":[104],"v":[{"k":[116],"v":[{"k":[116],"v":[{"k":[112],"v":[{"k":[115],"v":[{"k":[58],"v":[{"k":[47],"v":[{"k":[47],"v":[{"k":[103],"v":[{"k":[105],"v":[{"k":[116],"v":[{"k":[104],"v":[{"k":[117],"v":[{"k":[98],"v":[{"k":[46],"v":[{"k":[99],"v":[{"k":[111],"v":[{"k":[109],"v":[{"k":[47],"v":[{"k":[108],"v":[{"k":[105],"v":[{"k":[110],"v":[{"k":[117],"v":[{"k":[115],"v":[{"k":[98],"v":[{"k":[111],"v":[{"k":[114],"v":[{"k":[103],"v":[{"k":[47],"v":[{"k":[112],"v":[{"k":[111],"v":[{"k":[114],"v":[{"k":[116],"v":[{"k":[97],"v":[{"k":[108],"v":[{"k":[45],"v":[{"k":[118],"v":[{"k":[117],"v":[{"k":[101],"v":[{"k":[41],"v":[{"d":{"df":1,"dc":[[1,1]]}}]}]}]}]}]}]}]}]}]}]}]}]}]}]}]}]}]}]}]}]}]}]}]}]}]}]}]}]}]}]}]}]}]}]}]}]}]}]}]}]}]}]}]}]}]}]}]}]}]},{"k":[117],"v":[{"k":[103],"v":[{"k":[103],"v":[{"k":[97],"v":[{"k":[98],"v":[{"k":[108],"v":[{"k":[101],"v":[{"d":{"df":1,"dc":[[1,1]]}}]}]}]}]}]}]}]}]},{"k":[97],"v":[{"k":[105],"v":[{"k":[108],"v":[{"k":[119],"v":[{"k":[105],"v":[{"k":[110],"v":[{"k":[100],"v":[{"d":{"df":1,"dc":[[1,2]]}}]}]}]}]}]}]}]},{"k":[111],"v":[{"k":[110],"v":[{"k":[116],"v":[{"d":{"df":1,"dc":[[1,1]]}}]}]}]},{"k":[105,111],"v":[{"k":[109],"v":[{"k":[112],"v":[{"k":[108],"v":[{"k":[101],"v":[{"d":{"df":1,"dc":[[1,1]]}}]}]}]}]},{"k":[117],"v":[{"k":[114],"v":[{"k":[99],"v":[{"k":[101],"v":[{"k":[93],"v":[{"d":{"df":1,"dc":[[4,1]]}}]}]}]}]}]}]},{"k":[111],"v":[{"k":[100],"v":[{"k":[97],"v":[{"k":[115],"v":[{"k":[104],"v":[{"k":[93],"v":[{"k":[40],"v":[{"k":[104],"v":[{"k":[116],"v":[{"k":[116],"v":[{"k":[112],"v":[{"k":[115],"v":[{"k":[58],"v":[{"k":[47],"v":[{"k":[47],"v":[{"k":[108],"v":[{"k":[111],"v":[{"k":[100],"v":[{"k":[97],"v":[{"k":[115],"v":[{"k":[104],"v":[{"k":[46],"v":[{"k":[99],"v":[{"k":[111],"v":[{"k":[109],"v":[{"k":[47],"v":[{"k":[41],"v":[{"d":{"df":1,"dc":[[1,1]]}}]}]}]}]}]}]}]}]}]}]}]}]}]}]}]}]}]}]}]}]}]}]}]}]}]}]}]}]},{"d":{"df":2,"dc":[[1,1],[2,2]]}},{"k":[110,118,112,102,114,117,116,119,108],"v":[{"d":{"df":3,"dc":[[1,1],[4,1],[5,2]]},"k":[101],"v":[{"d":{"df":1,"dc":[[1,1]]}}]},{"k":[101],"v":[{"k":[114],"v":[{"k":[119,114],"v":[{"k":[114],"v":[{"k":[105],"v":[{"k":[116],"v":[{"k":[101,116],"v":[{"d":{"df":2,"dc":[[1,2],[5,1]]},"k":[97],"v":[{"k":[98],"v":[{"k":[108],"v":[{"k":[101],"v":[{"d":{"df":1,"dc":[[1,1]]}}]}]}]}]},{"k":[101],"v":[{"k":[110],"v":[{"k":[46],"v":[{"d":{"df":1,"dc":[[1,1]]}}]}]}]}]}]}]}]},{"k":[105],"v":[{"k":[100],"v":[{"k":[101],"v":[{"d":{"df":1,"dc":[[1,2]]}}]}]}]}]}]}]},{"k":[116,101],"v":[{"k":[105],"v":[{"k":[111],"v":[{"k":[110],"v":[{"k":[46],"v":[{"d":{"df":1,"dc":[[1,1]]}}]}]}]}]},{"k":[110],"v":[{"k":[103],"v":[{"k":[114],"v":[{"k":[97],"v":[{"k":[112],"v":[{"k":[104],"v":[{"d":{"df":1,"dc":[[4,1]]}}]}]}]}]}]}]}]},{"d":{"df":3,"dc":[[1,6],[4,2],[5,3]]},"k":[46,102],"v":[{"d":{"df":1,"dc":[[1,1]]},"k":[46],"v":[{"k":[46],"v":[{"d":{"df":1,"dc":[[1,1]]}}]}]},{"k":[101],"v":[{"k":[114],"v":[{"k":[101],"v":[{"k":[100],"v":[{"d":{"df":1,"dc":[[1,1]]}}]}]}]}]}]},{"d":{"df":2,"dc":[[1,3],[5,1]]},"k":[100],"v":[{"k":[101],"v":[{"k":[114],"v":[{"d":{"df":1,"dc":[[4,1]]}}]}]}]},{"k":[116],"v":[{"d":{"df":1,"dc":[[4,1]]}}]},{"k":[104],"v":[{"k":[101],"v":[{"k":[114],"v":[{"d":{"df":1,"dc":[[5,1]]},"k":[115],"v":[{"k":[46],"v":[{"k":[95],"v":[{"d":{"df":1,"dc":[[4,1]]}}]}]}]}]}]}]},{"k":[110],"v":[{"d":{"df":1,"dc":[[5,2]]}}]},{"k":[100],"v":[{"d":{"df":1,"dc":[[5,1]]}}]}]},{"k":[114,101,108,111,97,117,105],"v":[{"k":[101,111],"v":[{"k":[115],"v":[{"k":[101],"v":[{"k":[110],"v":[{"k":[116],"v":[{"k":[44],"v":[{"d":{"df":1,"dc":[[1,1]]}}]}]}]}]}]},{"k":[118,106,109,112],"v":[{"k":[105],"v":[{"k":[100],"v":[{"k":[101],"v":[{"d":{"df":1,"dc":[[1,2]]},"k":[115,33],"v":[{"d":{"df":1,"dc":[[1,1]]}},{"d":{"df":1,"dc":[[1,1]]}}]}]}]}]},{"k":[101],"v":[{"k":[99],"v":[{"k":[116],"v":[{"d":{"df":2,"dc":[[1,1],[5,1]]},"k":[58,44],"v":[{"d":{"df":1,"dc":[[5,2]]}},{"d":{"df":1,"dc":[[5,1]]}}]}]}]}]},{"k":[105],"v":[{"k":[115],"v":[{"k":[101],"v":[{"k":[115],"v":[{"d":{"df":1,"dc":[[1,2]]}}]}]}]}]},{"k":[101],"v":[{"k":[114],"v":[{"k":[108],"v":[{"k":[121],"v":[{"k":[46],"v":[{"d":{"df":1,"dc":[[4,1]]}}]}]}]}]}]}]}]},{"k":[114],"v":[{"k":[104],"v":[{"k":[97],"v":[{"k":[112],"v":[{"k":[115],"v":[{"d":{"df":1,"dc":[[1,1]]}}]}]}]}]}]},{"k":[97,117],"v":[{"k":[110,99,105],"v":[{"k":[110],"v":[{"k":[101],"v":[{"k":[100],"v":[{"d":{"df":1,"dc":[[1,1]]}}]}]}]},{"k":[101],"v":[{"d":{"df":1,"dc":[[5,1]]}}]},{"k":[110],"v":[{"d":{"df":1,"dc":[[5,1]]}}]}]},{"k":[103],"v":[{"k":[105],"v":[{"k":[110],"v":[{"d":{"df":1,"dc":[[1,1]]},"k":[44,46],"v":[{"d":{"df":1,"dc":[[1,1]]}},{"d":{"df":1,"dc":[[1,1]]}}]}]}]}]}]},{"k":[119,115],"v":[{"k":[101],"v":[{"k":[114],"v":[{"k":[102],"v":[{"k":[117],"v":[{"k":[108],"v":[{"k":[46],"v":[{"d":{"df":1,"dc":[[1,1]]}}]}]}]}]}]}]},{"k":[116],"v":[{"k":[99],"v":[{"k":[115],"v":[{"k":[115],"v":[{"d":{"df":1,"dc":[[2,1]]},"k":[59],"v":[{"d":{"df":1,"dc":[[5,1]]}}]}]}]}]}]}]},{"k":[114,103],"v":[{"k":[116],"v":[{"k":[105],"v":[{"k":[99,97],"v":[{"k":[117],"v":[{"k":[108],"v":[{"k":[97],"v":[{"k":[114],"v":[{"k":[44],"v":[{"d":{"df":1,"dc":[[1,1]]}}]}]}]}]}]},{"k":[108],"v":[{"d":{"df":1,"dc":[[1,1]]}}]}]}]}]},{"k":[101],"v":[{"d":{"df":2,"dc":[[1,1],[4,2]]},"k":[115],"v":[{"d":{"df":2,"dc":[[1,1],[5,2]]}}]}]}]},{"k":[103],"v":[{"d":{"df":1,"dc":[[2,1]]}}]},{"k":[99],"v":[{"k":[107],"v":[{"k":[101],"v":[{"k":[100],"v":[{"d":{"df":1,"dc":[[4,1]]}}]}]}]}]}]},{"k":[97,116,108,120,118,110],"v":[{"k":[99],"v":[{"k":[104],"v":[{"d":{"df":1,"dc":[[1,1]]}}]}]},{"k":[99],"v":[{"k":[46],"v":[{"k":[41],"v":[{"d":{"df":1,"dc":[[1,1]]}}]}]}]},{"k":[115],"v":[{"k":[101],"v":[{"k":[119],"v":[{"k":[104],"v":[{"k":[101],"v":[{"k":[114],"v":[{"k":[101],"v":[{"d":{"df":1,"dc":[[1,1]]}}]}]}]}]}]}]}]},{"k":[105,116,112,99,97],"v":[{"k":[115],"v":[{"k":[116],"v":[{"k":[101,105],"v":[{"k":[110],"v":[{"k":[99],"v":[{"k":[101],"v":[{"d":{"df":1,"dc":[[1,1]]}}]}]}]},{"k":[110],"v":[{"k":[103],"v":[{"d":{"df":1,"dc":[[1,1]]}}]}]}]}]}]},{"k":[101],"v":[{"k":[110],"v":[{"k":[100],"v":[{"d":{"df":1,"dc":[[1,1]]},"k":[105],"v":[{"k":[98],"v":[{"k":[108],"v":[{"k":[101],"v":[{"d":{"df":1,"dc":[[1,1]]}}]}]}]}]}]}]}]},{"k":[111],"v":[{"k":[115],"v":[{"k":[101],"v":[{"d":{"df":1,"dc":[[1,1]]}}]}]}]},{"k":[101],"v":[{"k":[112],"v":[{"k":[116],"v":[{"k":[105],"v":[{"k":[111],"v":[{"k":[110],"v":[{"d":{"df":1,"dc":[[4,1]]}}]}]}]}]}]}]},{"k":[109],"v":[{"k":[112],"v":[{"k":[108],"v":[{"k":[101],"v":[{"d":{"df":1,"dc":[[5,1]]}}]}]}]}]}]},{"k":[101],"v":[{"k":[110],"v":[{"d":{"df":1,"dc":[[1,1]]}}]}]},{"k":[97],"v":[{"k":[98],"v":[{"k":[108],"v":[{"k":[101],"v":[{"d":{"df":1,"dc":[[1,1]]}}]}]}]}]}]},{"k":[99,105,49,109],"v":[{"k":[108,117],"v":[{"k":[97],"v":[{"k":[115],"v":[{"k":[115],"v":[{"k":[105],"v":[{"k":[99],"v":[{"k":[41],"v":[{"d":{"df":1,"dc":[[1,1]]}}]}]}]}]}]}]},{"k":[115],"v":[{"k":[116],"v":[{"k":[111],"v":[{"k":[109],"v":[{"d":{"df":1,"dc":[[1,1]]}}]}]}]}]}]},{"d":{"df":1,"dc":[[1,1]]},"k":[110],"v":[{"k":[115],"v":[{"k":[116],"v":[{"k":[97],"v":[{"k":[108],"v":[{"k":[108],"v":[{"k":[101],"v":[{"k":[100],"v":[{"d":{"df":1,"dc":[[2,1]]}}]}]}]}]}]}]}]}]},{"k":[57],"v":[{"k":[50],"v":[{"k":[48],"v":[{"k":[120],"v":[{"k":[49],"v":[{"k":[48],"v":[{"k":[56],"v":[{"k":[48],"v":[{"k":[41],"v":[{"k":[46],"v":[{"d":{"df":1,"dc":[[4,1]]}}]}]}]}]}]}]}]}]}]}]},{"k":[97],"v":[{"k":[121],"v":[{"k":[98],"v":[{"k":[101],"v":[{"d":{"df":1,"dc":[[4,1]]}}]}]}]}]}]},{"k":[101,111,114,105,121],"v":[{"k":[101,118,112,102,99],"v":[{"k":[112],"v":[{"k":[108],"v":[{"k":[121],"v":[{"d":{"df":1,"dc":[[1,3]]}}]}]}]},{"d":{"df":1,"dc":[[4,1]]}},{"k":[101,108],"v":[{"k":[110],"v":[{"k":[100],"v":[{"k":[101],"v":[{"k":[110],"v":[{"k":[99],"v":[{"k":[121],"v":[{"k":[44],"v":[{"d":{"df":1,"dc":[[4,1]]}}]}]}]}]}]}]}]},{"k":[111],"v":[{"k":[121],"v":[{"d":{"df":1,"dc":[[4,1]]}}]}]}]},{"k":[97],"v":[{"k":[117],"v":[{"k":[108],"v":[{"k":[116],"v":[{"d":{"df":2,"dc":[[4,2],[5,2]]}}]}]}]}]},{"k":[108],"v":[{"k":[97],"v":[{"k":[114],"v":[{"k":[101],"v":[{"d":{"df":1,"dc":[[5,1]]}}]}]}]}]}]},{"d":{"df":1,"dc":[[4,1]]},"k":[101,110,99],"v":[{"k":[115],"v":[{"d":{"df":2,"dc":[[1,1],[4,1]]},"k":[110],"v":[{"k":[39],"v":[{"k":[116],"v":[{"d":{"df":1,"dc":[[1,1]]}}]}]}]}]},{"k":[101],"v":[{"d":{"df":1,"dc":[[5,1]]}}]},{"k":[115],"v":[{"k":[46],"v":[{"d":{"df":1,"dc":[[5,1]]}}]}]}]},{"k":[111],"v":[{"k":[112],"v":[{"k":[45],"v":[{"k":[105],"v":[{"k":[110],"v":[{"d":{"df":1,"dc":[[1,1]]}}]}]}]}]}]},{"k":[114,109],"v":[{"k":[101],"v":[{"k":[99],"v":[{"k":[116],"v":[{"k":[111],"v":[{"k":[114],"v":[{"k":[105,121],"v":[{"k":[101],"v":[{"k":[115],"v":[{"k":[46],"v":[{"d":{"df":1,"dc":[[1,1]]}}]}]}]},{"d":{"df":2,"dc":[[4,1],[5,1]]}}]}]}]}]}]}]},{"k":[101],"v":[{"k":[110],"v":[{"k":[115],"v":[{"k":[105],"v":[{"k":[111],"v":[{"k":[110],"v":[{"k":[115],"v":[{"d":{"df":1,"dc":[[4,1]]}}]}]}]}]}]}]}]}]},{"k":[110],"v":[{"k":[97],"v":[{"k":[109],"v":[{"k":[105],"v":[{"k":[99],"v":[{"d":{"df":1,"dc":[[1,1]]}}]}]}]}]}]}]},{"k":[97,117,101],"v":[{"k":[108],"v":[{"k":[117],"v":[{"k":[101],"v":[{"k":[115],"v":[{"d":{"df":1,"dc":[[1,1]]}}]}]}]}]},{"k":[101],"v":[{"d":{"df":3,"dc":[[1,2],[2,3],[5,3]]}}]},{"k":[114],"v":[{"k":[121],"v":[{"d":{"df":1,"dc":[[5,1]]}}]}]}]},{"k":[114,112,115,60,121,39,116,110,96,97,64],"v":[{"k":[111],"v":[{"k":[99],"v":[{"k":[107],"v":[{"k":[98],"v":[{"k":[97],"v":[{"k":[110],"v":[{"k":[100],"v":[{"k":[46],"v":[{"k":[99],"v":[{"k":[111,115],"v":[{"k":[110],"v":[{"k":[102],"v":[{"k":[105],"v":[{"k":[103],"v":[{"k":[46],"v":[{"k":[106],"v":[{"k":[115],"v":[{"k":[96],"v":[{"k":[44],"v":[{"d":{"df":1,"dc":[[1,1]]}}]}]}]}]}]}]}]}]}]},{"k":[115],"v":[{"k":[96],"v":[{"d":{"df":1,"dc":[[5,1]]}}]}]}]}]}]}]}]}]}]}]}]}]},{"k":[97],"v":[{"k":[103],"v":[{"k":[101],"v":[{"k":[115],"v":[{"k":[47],"v":[{"k":[96],"v":[{"d":{"df":1,"dc":[[1,1]]}}]}]}]}]}]}]},{"k":[116],"v":[{"k":[111],"v":[{"k":[114],"v":[{"k":[101],"v":[{"k":[47],"v":[{"k":[96],"v":[{"d":{"df":1,"dc":[[1,1]]}}]}]}]}]}]}]},{"k":[112],"v":[{"k":[111],"v":[{"k":[114],"v":[{"k":[116],"v":[{"k":[97],"v":[{"k":[108],"v":[{"k":[62],"v":[{"k":[96],"v":[{"d":{"df":1,"dc":[[1,1]]}}]}]}]}]}]}]}]}]},{"k":[97],"v":[{"k":[114],"v":[{"k":[110],"v":[{"d":{"df":1,"dc":[[4,1]]}}]}]}]},{"k":[64],"v":[{"k":[114],"v":[{"k":[111],"v":[{"k":[99],"v":[{"k":[107],"v":[{"k":[98],"v":[{"k":[97],"v":[{"k":[110],"v":[{"k":[100],"v":[{"k":[47],"v":[{"k":[118],"v":[{"k":[117],"v":[{"k":[101],"v":[{"k":[39],"v":[{"k":[96],"v":[{"d":{"df":1,"dc":[[4,1]]}}]}]}]}]}]}]}]}]}]}]}]}]}]}]}]},{"k":[110,97],"v":[{"k":[116],"v":[{"k":[46],"v":[{"k":[99,102],"v":[{"k":[111],"v":[{"k":[110],"v":[{"k":[102],"v":[{"k":[105],"v":[{"k":[103],"v":[{"k":[46],"v":[{"k":[106],"v":[{"k":[115],"v":[{"k":[96],"v":[{"d":{"df":1,"dc":[[4,1]]},"k":[44],"v":[{"d":{"df":1,"dc":[[4,1]]}}]}]}]}]}]}]}]}]}]}]},{"k":[101],"v":[{"k":[101],"v":[{"k":[100],"v":[{"k":[46],"v":[{"k":[106],"v":[{"k":[115],"v":[{"k":[96],"v":[{"k":[41],"v":[{"d":{"df":1,"dc":[[4,1]]}}]}]}]}]}]}]}]}]}]}]}]},{"k":[105],"v":[{"k":[108],"v":[{"k":[119],"v":[{"k":[105],"v":[{"k":[110],"v":[{"k":[100],"v":[{"k":[46],"v":[{"k":[99],"v":[{"k":[111],"v":[{"k":[110],"v":[{"k":[102],"v":[{"k":[105],"v":[{"k":[103],"v":[{"k":[46],"v":[{"k":[106],"v":[{"k":[115],"v":[{"k":[96],"v":[{"d":{"df":1,"dc":[[5,1]]},"k":[44],"v":[{"d":{"df":1,"dc":[[4,1]]}}]}]}]}]}]}]}]}]}]}]}]}]}]}]}]}]}]}]}]},{"k":[117],"v":[{"k":[120],"v":[{"k":[116],"v":[{"k":[46],"v":[{"k":[102,99],"v":[{"k":[101],"v":[{"k":[101],"v":[{"k":[100],"v":[{"k":[46],"v":[{"k":[106],"v":[{"k":[115],"v":[{"k":[96],"v":[{"d":{"df":1,"dc":[[4,1]]}}]}]}]}]}]}]}]},{"k":[111],"v":[{"k":[110],"v":[{"k":[102],"v":[{"k":[105],"v":[{"k":[103],"v":[{"k":[46],"v":[{"k":[106],"v":[{"k":[115],"v":[{"k":[96],"v":[{"d":{"df":1,"dc":[[4,1]]},"k":[58],"v":[{"d":{"df":1,"dc":[[5,1]]}}]}]}]}]}]}]}]}]}]}]}]}]}]}]}]},{"k":[96],"v":[{"d":{"df":1,"dc":[[5,5]]},"k":[115,106,99],"v":[{"k":[104],"v":[{"d":{"df":1,"dc":[[5,3]]}}]},{"k":[115],"v":[{"d":{"df":1,"dc":[[5,1]]}}]},{"k":[115],"v":[{"k":[115],"v":[{"d":{"df":1,"dc":[[5,1]]}}]}]}]}]},{"k":[115],"v":[{"k":[115],"v":[{"k":[101],"v":[{"k":[116],"v":[{"k":[115],"v":[{"k":[47],"v":[{"k":[99],"v":[{"k":[115],"v":[{"k":[115],"v":[{"k":[47],"v":[{"k":[114],"v":[{"k":[111],"v":[{"k":[99],"v":[{"k":[107],"v":[{"k":[98],"v":[{"k":[97],"v":[{"k":[110],"v":[{"k":[100],"v":[{"k":[46],"v":[{"k":[99],"v":[{"k":[115],"v":[{"k":[115],"v":[{"k":[96],"v":[{"d":{"df":1,"dc":[[5,1]]}}]}]}]}]}]}]}]}]}]}]}]}]}]}]}]}]}]}]}]}]}]}]}]},{"k":[114],"v":[{"k":[111],"v":[{"k":[99],"v":[{"k":[107],"v":[{"k":[98],"v":[{"k":[97],"v":[{"k":[110],"v":[{"k":[100],"v":[{"k":[47],"v":[{"k":[118],"v":[{"k":[117],"v":[{"k":[101],"v":[{"k":[96],"v":[{"k":[58],"v":[{"d":{"df":1,"dc":[[5,1]]}}]}]}]}]}]}]}]}]}]}]}]}]}]}]}]},{"k":[115,116],"v":[{"k":[101],"v":[{"d":{"df":1,"dc":[[1,1]]},"k":[115],"v":[{"d":{"df":1,"dc":[[1,1]]}}]}]},{"k":[105],"v":[{"k":[108],"v":[{"k":[105],"v":[{"k":[122],"v":[{"k":[101],"v":[{"d":{"df":1,"dc":[[4,1]]}}]}]}]}]}]}]},{"k":[101,111,97],"v":[{"k":[116],"v":[{"d":{"df":1,"dc":[[1,1]]}}]},{"k":[117],"v":[{"d":{"df":1,"dc":[[5,4]]},"k":[114,39],"v":[{"d":{"df":2,"dc":[[1,1],[5,5]]}},{"k":[108],"v":[{"k":[108],"v":[{"d":{"df":1,"dc":[[5,1]]}}]}]}]}]},{"k":[114],"v":[{"k":[110],"v":[{"d":{"df":1,"dc":[[5,2]]}}]}]}]},{"k":[109,115,116,110],"v":[{"k":[101],"v":[{"k":[97],"v":[{"k":[110],"v":[{"k":[116],"v":[{"k":[95],"v":[{"d":{"df":1,"dc":[[1,1]]}}]}]}]}]}]},{"k":[117],"v":[{"k":[112],"v":[{"k":[112],"v":[{"k":[111],"v":[{"k":[114],"v":[{"k":[116],"v":[{"k":[115],"v":[{"d":{"df":1,"dc":[[2,1]]}}]}]}]}]}]}]}]},{"k":[104],"v":[{"k":[105],"v":[{"k":[115],"v":[{"d":{"df":1,"dc":[[4,1]]}}]}]}]},{"k":[111],"v":[{"k":[116],"v":[{"k":[101],"v":[{"k":[58],"v":[{"d":{"df":1,"dc":[[4,1]]}}]}]}]}]}]},{"d":{"df":1,"dc":[[1,2]]}},{"d":{"df":1,"dc":[[1,2]]}},{"k":[112,64],"v":[{"k":[111],"v":[{"k":[114],"v":[{"k":[116],"v":[{"k":[97],"v":[{"k":[108],"v":[{"k":[115],"v":[{"k":[34],"v":[{"d":{"df":1,"dc":[[1,1]]}}]}]}]}]}]}]}]},{"k":[114],"v":[{"k":[111],"v":[{"k":[99],"v":[{"k":[107],"v":[{"k":[98],"v":[{"k":[97],"v":[{"k":[110],"v":[{"k":[100],"v":[{"k":[47],"v":[{"k":[118],"v":[{"k":[117],"v":[{"k":[101],"v":[{"k":[34],"v":[{"k":[59],"v":[{"d":{"df":1,"dc":[[5,1]]}}]}]}]}]}]}]}]}]}]}]}]}]}]}]}]},{"k":[42,47],"v":[{"k":[105,99],"v":[{"k":[110],"v":[{"k":[115],"v":[{"k":[116],"v":[{"k":[97],"v":[{"k":[108],"v":[{"k":[108],"v":[{"k":[97],"v":[{"k":[116],"v":[{"k":[105],"v":[{"k":[111],"v":[{"k":[110],"v":[{"k":[58],"v":[{"k":[42],"v":[{"k":[42],"v":[{"d":{"df":1,"dc":[[4,1]]}}]}]}]}]}]}]}]}]}]}]}]}]}]}]},{"k":[111],"v":[{"k":[110],"v":[{"k":[102],"v":[{"k":[105],"v":[{"k":[103],"v":[{"k":[117],"v":[{"k":[114],"v":[{"k":[97],"v":[{"k":[116],"v":[{"k":[105],"v":[{"k":[111],"v":[{"k":[110],"v":[{"k":[58],"v":[{"k":[42],"v":[{"k":[42],"v":[{"d":{"df":1,"dc":[[4,1]]}}]}]}]}]}]}]}]}]}]}]}]}]}]}]}]}]},{"d":{"df":1,"dc":[[5,1]]}}]},{"k":[114,105],"v":[{"k":[111],"v":[{"k":[99],"v":[{"k":[107],"v":[{"k":[98],"v":[{"k":[97],"v":[{"k":[110],"v":[{"k":[100],"v":[{"k":[47],"v":[{"k":[118,110],"v":[{"k":[117],"v":[{"k":[101],"v":[{"d":{"df":1,"dc":[[5,2]]}}]}]},{"k":[117],"v":[{"k":[120],"v":[{"k":[116],"v":[{"d":{"df":1,"dc":[[5,1]]}}]}]}]}]}]}]}]}]}]}]}]}]},{"k":[109],"v":[{"k":[112],"v":[{"k":[111],"v":[{"k":[114],"v":[{"k":[116],"v":[{"d":{"df":1,"dc":[[5,1]]}}]}]}]}]}]}]},{"k":[64,100,98],"v":[{"k":[114],"v":[{"k":[111],"v":[{"k":[99],"v":[{"k":[107],"v":[{"k":[98],"v":[{"k":[97],"v":[{"k":[110],"v":[{"k":[100],"v":[{"k":[47],"v":[{"k":[110],"v":[{"k":[117],"v":[{"k":[120],"v":[{"k":[116],"v":[{"k":[39],"v":[{"d":{"df":1,"dc":[[5,1]]}}]}]}]}]}]}]}]}]}]}]}]}]}]}]},{"k":[111],"v":[{"k":[99],"v":[{"k":[115],"v":[{"k":[39],"v":[{"d":{"df":1,"dc":[[5,1]]}}]}]}]}]},{"k":[108],"v":[{"k":[111],"v":[{"k":[103],"v":[{"k":[39],"v":[{"k":[46],"v":[{"d":{"df":1,"dc":[[5,1]]}}]}]}]}]}]}]},{"d":{"df":1,"dc":[[5,1]]}},{"k":[42],"v":[{"d":{"df":1,"dc":[[5,1]]}}]},{"k":[117],"v":[{"k":[115],"v":[{"k":[116],"v":[{"d":{"df":1,"dc":[[5,2]]}}]}]}]}]}}}}}],"databaseVersion":1.5,"engineVersion":1.5,"filename":"content.db","_persistenceAdapter":null,"_persistenceMethod":null,"_throttledSaves":true}